Workbook

Sheet Notes
A1: Cleaning & postcode coding notes
A3: Dataset | B3: Rows in | C3: Rows out | D3: Postcode method
A4: EV chargers (ev_20251216_updated.csv) | B4: 1958 | C4: 1958 | D4: Parsed from street address (1,956); original PCODE used where address had none (1); nearest-point inference (1)
A5: Transport stops (locationfacilitydata.csv) | B5: 797 | C5: 797 | D5: Parsed from address (796); 1 address had no postcode, filled from nearest EV charger
A6: Sports facilities (table.xlsx) | B6: 70 | C6: 70 | D6: Postcode supplied in source
A7: Taxi ranks (taxi-rank-locations_0.csv) | B7: 199 | C7: 198 | D7: No postcode in source. Inferred from nearest EV/transport point with a known postcode. See Postcode_confidence; treat "low" as needing a manual check
A8: Building complexes (BuildingComplexPoint.csv) | B8: 76629 | C8: 76628 | D8: NOT coded: file has no coordinates, address or postcode (only names/codes). Cleaned separately as building_complex_cleaned.csv
A10: Cleaning applied
A11: - Collapsed line breaks / extra whitespace in addresses and text; trimmed; blanks to empty
A12: - EV: removed trailing ", Australia" from addresses; standardised "NRMA Electric" to "NRMA"; added Max_rating_kW (parsed from Charger_rating) and Is_upcoming
A13: - EV: 25 rows had an original PCODE that contradicted the address postcode (e.g. Wilcannia address says 2836, PCODE said 2350). Address postcode used; flagged in PCODE_conflict
A14: - Transport: standardised MORNING_PEAK "6.30-10am" to "6.30am-10am"; deduplicated on TSN
A15: - Sports: postcodes stored as numbers; text tidied
A16: - Buildings: dropped fully empty and constant columns, parsed dates, removed 1 duplicate topoid
A18: Caveats
A19: - 18 transport stops and 2 EV chargers have postcodes outside NSW/ACT (interstate coach stops, e.g. Melbourne, Brisbane). They are genuine, not errors.
A20: - Summary_by_Postcode uses live COUNTIF/SUMIF formulas against the data sheets. Sports facilities cover only City of Sydney area postcodes.

Sheet Summary_by_Postcode
A1: Postcode | B1: EV stations | C1: EV plugs | D1: Transport stops | E1: Sports facilities | F1: Taxi ranks | G1: Total points | H1: Datasets present
A2: 2000 | B2: =COUNTIF(EV_Chargers!$D:$D,A2) -> 29 | C2: =SUMIF(EV_Chargers!$D:$D,A2,EV_Chargers!$I:$I) -> 102 | D2: =COUNTIF(Transport_Stops!$E:$E,A2) -> 22 | E2: =COUNTIF(Sports_Facilities!$C:$C,A2) -> 9 | F2: =COUNTIF(Taxi_Ranks!$B:$B,A2) -> 27 | G2: =B2+D2+E2+F2 -> 87 | H2: =(B2>0)+(D2>0)+(E2>0)+(F2>0) -> 4
A3: 2007 | B3: =COUNTIF(EV_Chargers!$D:$D,A3) -> 3 | C3: =SUMIF(EV_Chargers!$D:$D,A3,EV_Chargers!$I:$I) -> 7 | D3: =COUNTIF(Transport_Stops!$E:$E,A3) -> 0 | E3: =COUNTIF(Sports_Facilities!$C:$C,A3) -> 2 | F3: =COUNTIF(Taxi_Ranks!$B:$B,A3) -> 0 | G3: =B3+D3+E3+F3 -> 5 | H3: =(B3>0)+(D3>0)+(E3>0)+(F3>0) -> 2
A4: 2008 | B4: =COUNTIF(EV_Chargers!$D:$D,A4) -> 2 | C4: =SUMIF(EV_Chargers!$D:$D,A4,EV_Chargers!$I:$I) -> 6 | D4: =COUNTIF(Transport_Stops!$E:$E,A4) -> 1 | E4: =COUNTIF(Sports_Facilities!$C:$C,A4) -> 2 | F4: =COUNTIF(Taxi_Ranks!$B:$B,A4) -> 0 | G4: =B4+D4+E4+F4 -> 5 | H4: =(B4>0)+(D4>0)+(E4>0)+(F4>0) -> 3
A5: 2009 | B5: =COUNTIF(EV_Chargers!$D:$D,A5) -> 2 | C5: =SUMIF(EV_Chargers!$D:$D,A5,EV_Chargers!$I:$I) -> 4 | D5: =COUNTIF(Transport_Stops!$E:$E,A5) -> 8 | E5: =COUNTIF(Sports_Facilities!$C:$C,A5) -> 3 | F5: =COUNTIF(Taxi_Ranks!$B:$B,A5) -> 3 | G5: =B5+D5+E5+F5 -> 16 | H5: =(B5>0)+(D5>0)+(E5>0)+(F5>0) -> 4
A6: 2010 | B6: =COUNTIF(EV_Chargers!$D:$D,A6) -> 8 | C6: =SUMIF(EV_Chargers!$D:$D,A6,EV_Chargers!$I:$I) -> 16 | D6: =COUNTIF(Transport_Stops!$E:$E,A6) -> 1 | E6: =COUNTIF(Sports_Facilities!$C:$C,A6) -> 5 | F6: =COUNTIF(Taxi_Ranks!$B:$B,A6) -> 2 | G6: =B6+D6+E6+F6 -> 16 | H6: =(B6>0)+(D6>0)+(E6>0)+(F6>0) -> 4
A7: 2011 | B7: =COUNTIF(EV_Chargers!$D:$D,A7) -> 3 | C7: =SUMIF(EV_Chargers!$D:$D,A7,EV_Chargers!$I:$I) -> 9 | D7: =COUNTIF(Transport_Stops!$E:$E,A7) -> 2 | E7: =COUNTIF(Sports_Facilities!$C:$C,A7) -> 6 | F7: =COUNTIF(Taxi_Ranks!$B:$B,A7) -> 3 | G7: =B7+D7+E7+F7 -> 14 | H7: =(B7>0)+(D7>0)+(E7>0)+(F7>0) -> 4
A8: 2015 | B8: =COUNTIF(EV_Chargers!$D:$D,A8) -> 8 | C8: =SUMIF(EV_Chargers!$D:$D,A8,EV_Chargers!$I:$I) -> 25 | D8: =COUNTIF(Transport_Stops!$E:$E,A8) -> 3 | E8: =COUNTIF(Sports_Facilities!$C:$C,A8) -> 7 | F8: =COUNTIF(Taxi_Ranks!$B:$B,A8) -> 1 | G8: =B8+D8+E8+F8 -> 19 | H8: =(B8>0)+(D8>0)+(E8>0)+(F8>0) -> 4
A9: 2016 | B9: =COUNTIF(EV_Chargers!$D:$D,A9) -> 2 | C9: =SUMIF(EV_Chargers!$D:$D,A9,EV_Chargers!$I:$I) -> 12 | D9: =COUNTIF(Transport_Stops!$E:$E,A9) -> 0 | E9: =COUNTIF(Sports_Facilities!$C:$C,A9) -> 5 | F9: =COUNTIF(Taxi_Ranks!$B:$B,A9) -> 0 | G9: =B9+D9+E9+F9 -> 7 | H9: =(B9>0)+(D9>0)+(E9>0)+(F9>0) -> 2
A10: 2017 | B10: =COUNTIF(EV_Chargers!$D:$D,A10) -> 6 | C10: =SUMIF(EV_Chargers!$D:$D,A10,EV_Chargers!$I:$I) -> 25 | D10: =COUNTIF(Transport_Stops!$E:$E,A10) -> 1 | E10: =COUNTIF(Sports_Facilities!$C:$C,A10) -> 9 | F10: =COUNTIF(Taxi_Ranks!$B:$B,A10) -> 0 | G10: =B10+D10+E10+F10 -> 16 | H10: =(B10>0)+(D10>0)+(E10>0)+(F10>0) -> 3
A11: 2018 | B11: =COUNTIF(EV_Chargers!$D:$D,A11) -> 3 | C11: =SUMIF(EV_Chargers!$D:$D,A11,EV_Chargers!$I:$I) -> 14 | D11: =COUNTIF(Transport_Stops!$E:$E,A11) -> 0 | E11: =COUNTIF(Sports_Facilities!$C:$C,A11) -> 3 | F11: =COUNTIF(Taxi_Ranks!$B:$B,A11) -> 0 | G11: =B11+D11+E11+F11 -> 6 | H11: =(B11>0)+(D11>0)+(E11>0)+(F11>0) -> 2
A12: 2019 | B12: =COUNTIF(EV_Chargers!$D:$D,A12) -> 3 | C12: =SUMIF(EV_Chargers!$D:$D,A12,EV_Chargers!$I:$I) -> 6 | D12: =COUNTIF(Transport_Stops!$E:$E,A12) -> 0 | E12: =COUNTIF(Sports_Facilities!$C:$C,A12) -> 0 | F12: =COUNTIF(Taxi_Ranks!$B:$B,A12) -> 0 | G12: =B12+D12+E12+F12 -> 3 | H12: =(B12>0)+(D12>0)+(E12>0)+(F12>0) -> 1
A13: 2020 | B13: =COUNTIF(EV_Chargers!$D:$D,A13) -> 11 | C13: =SUMIF(EV_Chargers!$D:$D,A13,EV_Chargers!$I:$I) -> 35 | D13: =COUNTIF(Transport_Stops!$E:$E,A13) -> 3 | E13: =COUNTIF(Sports_Facilities!$C:$C,A13) -> 0 | F13: =COUNTIF(Taxi_Ranks!$B:$B,A13) -> 1 | G13: =B13+D13+E13+F13 -> 15 | H13: =(B13>0)+(D13>0)+(E13>0)+(F13>0) -> 3
... A544: 5000 | B544: =COUNTIF(EV_Chargers!$D:$D,A544) -> 0 | C544: =SUMIF(EV_Chargers!$D:$D,A544,EV_Chargers!$I:$I) -> 0 | D544: =COUNTIF(Transport_Stops!$E:$E,A544) -> 2 | E544: =COUNTIF(Sports_Facilities!$C:$C,A544) -> 0 | F544: =COUNTIF(Taxi_Ranks!$B:$B,A544) -> 0 | G544: =B544+D544+E544+F544 -> 2 | H544: =(B544>0)+(D544>0)+(E544>0)+(F544>0) -> 1
A545: TOTAL | B545: =SUM(B2:B544) -> 1958 | C545: =SUM(C2:C544) -> 5626 | D545: =SUM(D2:D544) -> 797 | E545: =SUM(E2:E544) -> 70 | F545: =SUM(F2:F544) -> 198 | G545: =SUM(G2:G544) -> 3023

Sheet EV_Chargers
A1: OBJECTID | B1: Station_name | C1: Station_address | D1: Postcode | E1: Postcode_source | F1: PCODE_conflict | G1: LGANAME | H1: Operator | I1: Number_of_plugs | J1: Charger_Type | K1: Charger_rating | L1: Max_rating_kW | M1: Is_upcoming | N1: Source | O1: Latitude | P1: Longitude
A2: 1 | C2: 129 Pacific Hwy Ourimbah NSW 2258 | D2: 2258 | E2: parsed from address | F2: =FALSE() -> FALSE | H2: NRMA | I2: 4 | J2: Upcoming | K2: 2x350kW & 2x175kW | L2: 350 | M2: =TRUE() -> TRUE | O2: -33.353198 | P2: 151.36903
A3: 2 | C3: 1-5 Hill Rd Sydney Olympic Park NSW 2127 | D3: 2127 | E3: parsed from address | F3: =FALSE() -> FALSE | H3: NRMA | I3: 8 | J3: Upcoming | K3: 2x350kW & 6x175kW | L3: 350 | M3: =TRUE() -> TRUE | O3: -33.846599 | P3: 151.05673
A4: 3 | C4: 16 Cooper St Macksville NSW 2447 | D4: 2447 | E4: parsed from address | F4: =FALSE() -> FALSE | H4: NRMA | I4: 4 | J4: Upcoming | K4: 2x350kW & 2x175kW | L4: 350 | M4: =TRUE() -> TRUE | O4: -30.708461 | P4: 152.92007
A5: 4 | C5: 2 Macquarie St Parramatta NSW 2150 | D5: 2150 | E5: parsed from address | F5: =FALSE() -> FALSE | H5: NRMA | I5: 4 | J5: Upcoming | K5: 2x350kW & 2x175kW | L5: 350 | M5: =TRUE() -> TRUE | O5: -33.81384 | P5: 150.99951
A6: 5 | C6: 203 Holt Rd Taren Point NSW 2229 | D6: 2229 | E6: parsed from address | F6: =FALSE() -> FALSE | H6: NRMA | I6: 4 | J6: Upcoming | K6: 2x350kW & 2x175kW | L6: 350 | M6: =TRUE() -> TRUE | O6: -34.020269 | P6: 151.1171
A7: 6 | C7: 25 Anglo Rd Campsie NSW 2194 | D7: 2194 | E7: parsed from address | F7: =FALSE() -> FALSE | H7: NRMA | I7: 4 | J7: Upcoming | K7: 2x350kW & 2x175kW | L7: 350 | M7: =TRUE() -> TRUE | O7: -33.911201 | P7: 151.10146
A8: 7 | C8: 29 Church St, Maitland NSW 2320 | D8: 2320 | E8: parsed from address | F8: =FALSE() -> FALSE | H8: NRMA | I8: 4 | J8: Upcoming | K8: 2x350kW & 2x175kW | L8: 350 | M8: =TRUE() -> TRUE | O8: -32.732981 | P8: 151.55356
A9: 8 | C9: 33 Village Cct Gregory Hills NSW 2557 | D9: 2557 | E9: parsed from address | F9: =FALSE() -> FALSE | H9: NRMA | I9: 4 | J9: Upcoming | K9: 2x350kW & 2x175kW | L9: 350 | M9: =TRUE() -> TRUE | O9: -34.026258 | P9: 150.77773
A10: 9 | C10: 37-39 Bong Bong Street,, Dapto NSW 2023 | D10: 2023 | E10: parsed from address | F10: =FALSE() -> FALSE | H10: NRMA | I10: 4 | J10: Upcoming | K10: 2x350kW & 2x175kW | L10: 350 | M10: =TRUE() -> TRUE | O10: -34.494036 | P10: 150.79154
A11: 10 | C11: 3A Cowell St Gladesville NSW 2111 | D11: 2111 | E11: parsed from address | F11: =FALSE() -> FALSE | H11: NRMA | I11: 4 | J11: Upcoming | K11: 2x350kW & 2x175kW | L11: 350 | M11: =TRUE() -> TRUE | O11: -33.832583 | P11: 151.12802
A12: 11 | C12: 50 Pitt St Singleton NSW 2330 | D12: 2330 | E12: parsed from address | F12: =FALSE() -> FALSE | H12: NRMA | I12: 4 | J12: Upcoming | K12: 2x350kW & 2x175kW | L12: 350 | M12: =TRUE() -> TRUE | O12: -32.565117 | P12: 151.17446
A13: 12 | C13: 57 Manchester Rd Gymea NSW 2227 | D13: 2227 | E13: parsed from address | F13: =FALSE() -> FALSE | H13: NRMA | I13: 4 | J13: Upcoming | K13: 2x350kW & 2x175kW | L13: 350 | M13: =TRUE() -> TRUE | O13: -34.032498 | P13: 151.08811
... A16: 15 | C16: Clarence St, Moss Vale NSW 2577 | D16: 2577 | E16: parsed from address | F16: =FALSE() -> FALSE | H16: NRMA | I16: 4 | J16: Upcoming | K16: 2x350kW & 2x175kW | L16: 350 | M16: =TRUE() -> TRUE | O16: -34.548422 | P16: 150.37357
A17: 16 | C17: 1 - 7 Ross St, Wilcannia NSW 2836 | D17: 2836 | E17: parsed from address | F17: =TRUE() -> TRUE | G17: Central Darling Shire Council | H17: NRMA | I17: 4 | J17: DC | K17: 50 kW | L17: 50 | M17: =FALSE() -> FALSE | N17: TfNSW Regional | O17: -31.557629 | P17: 143.38601
A18: 17 | C18: 1 Kendall Ave, Bathurst, 2795 | D18: 2795 | E18: parsed from address | F18: =FALSE() -> FALSE | G18: Bathurst Regional Council | H18: NRMA | I18: 2 | J18: DC | K18: 50 kW | L18: 50 | M18: =FALSE() -> FALSE | N18: Existing Fast Chargers | O18: -33.419102 | P18: 149.58675
A19: 18 | C19: 1 Little Walker St, Casino, NSW 2470 | D19: 2470 | E19: parsed from address | F19: =TRUE() -> TRUE | G19: Richmond Valley Council | H19: NRMA | I19: 4 | J19: DC | K19: 50 kW | L19: 50 | M19: =FALSE() -> FALSE | N19: TfNSW Regional | O19: -28.865732 | P19: 153.04848
A20: 19 | C20: 10W Apsley St, Walcha NSW 2354 | D20: 2354 | E20: parsed from address | F20: =TRUE() -> TRUE | G20: Walcha Council | H20: NRMA | I20: 4 | J20: DC | K20: 50 kW | L20: 50 | M20: =FALSE() -> FALSE | N20: TfNSW Regional | O20: -30.98297 | P20: 151.59282
A21: 20 | C21: 11 Ewingsdale Rd, Ewingsdale, 2481 | D21: 2481 | E21: parsed from address | F21: =FALSE() -> FALSE | G21: Byron Shire Council | H21: NRMA | I21: 4 | J21: DC | K21: 75 kW | L21: 75 | M21: =FALSE() -> FALSE | N21: Existing Fast Chargers | O21: -28.636128 | P21: 153.55346
A22: 21 | C22: 116 Liverpool St, Scone, NSW 2337 | D22: 2337 | E22: parsed from address | F22: =TRUE() -> TRUE | G22: Upper Hunter Shire Council | H22: NRMA | I22: 2 | J22: DC | K22: 50 kW | L22: 50 | M22: =FALSE() -> FALSE | N22: TfNSW Regional | O22: -32.050429 | P22: 150.86667
A23: 22 | C23: 132 Pound Street, Grafton, 2460 | D23: 2460 | E23: parsed from address | F23: =FALSE() -> FALSE | G23: Clarence Valley Council | H23: NRMA | I23: 2 | J23: DC | K23: 50 kW | L23: 50 | M23: =FALSE() -> FALSE | N23: Existing Fast Chargers | O23: -29.68811 | P23: 152.93342
A24: 23 | C24: 134 Lachlan St, Hay, 2711 | D24: 2711 | E24: parsed from address | F24: =FALSE() -> FALSE | G24: Hay Shire Council | H24: NRMA | I24: 4 | J24: DC | K24: 180 kW | L24: 180 | M24: =FALSE() -> FALSE | N24: Existing Fast Chargers | O24: -34.508904 | P24: 144.84279
A25: 24 | C25: 134 Lachlan St, Hay, 2711 | D25: 2711 | E25: parsed from address | F25: =FALSE() -> FALSE | G25: Hay Shire Council | H25: NRMA | I25: 2 | J25: DC | K25: 50 kW | L25: 50 | M25: =FALSE() -> FALSE | N25: Existing Fast Chargers | O25: -34.50908 | P25: 144.84107
A26: 25 | C26: 140 Queen St, Berry, 2535 | D26: 2535 | E26: parsed from address | F26: =FALSE() -> FALSE | G26: Shoalhaven City Council | H26: NRMA | I26: 2 | J26: DC | K26: 50 kW | L26: 50 | M26: =FALSE() -> FALSE | N26: Existing Fast Chargers | O26: -34.775594 | P26: 150.70109
A27: 26 | C27: 15 Victory St, Braidwood, NSW 2622 | D27: 2622 | E27: parsed from address | F27: =TRUE() -> TRUE | G27: Queanbeyan-Palerang Regional Council | H27: NRMA | I27: 4 | J27: DC | K27: 50 kW | L27: 50 | M27: =FALSE() -> FALSE | N27: TfNSW Regional | O27: -35.442778 | P27: 149.79137
A28: 27 | C28: 157 Rouse Street, Tenterfield, NSW 2372 | D28: 2372 | E28: parsed from address | F28: =TRUE() -> TRUE | G28: Tenterfield Shire Council | H28: NRMA | I28: 2 | J28: DC | K28: 50 kW | L28: 50 | M28: =FALSE() -> FALSE | N28: TfNSW Regional | O28: -29.057341 | P28: 152.01889
A29: 28 | C29: 15c Mitchell St, Bourke, NSW 2840 | D29: 2840 | E29: parsed from address | F29: =TRUE() -> TRUE | G29: Bourke Shire Council | H29: NRMA | I29: 4 | J29: DC | K29: 75 kW | L29: 75 | M29: =FALSE() -> FALSE | N29: TfNSW Regional | O29: -30.088397 | P29: 145.93501
A30: 29 | C30: 16 Berry St, Nowra, 2541 | D30: 2541 | E30: parsed from address | F30: =FALSE() -> FALSE | G30: Shoalhaven City Council | H30: NRMA | I30: 4 | J30: DC | K30: 160 kW | L30: 160 | M30: =FALSE() -> FALSE | N30: Existing Fast Chargers | O30: -34.87369 | P30: 150.60038
A31: 30 | C31: 17 Stewart St, Wollongong NSW 2500 | D31: 2500 | E31: parsed from address | F31: =TRUE() -> TRUE | G31: Wollongong City Council | H31: NRMA | I31: 4 | J31: DC | K31: 75 kW | L31: 75 | M31: =FALSE() -> FALSE | N31: TfNSW Regional | O31: -34.428268 | P31: 150.90015
A32: 31 | C32: 18 Dandaloo St, Nyngan, NSW 2825 | D32: 2825 | E32: parsed from address | F32: =TRUE() -> TRUE | G32: Bogan Shire Council | H32: NRMA | I32: 4 | J32: DC | K32: 75 kW | L32: 75 | M32: =FALSE() -> FALSE | N32: TfNSW Regional | O32: -31.564331 | P32: 147.19701
A33: 32 | C33: 2 Perry St, Euston, 2737 | D33: 2737 | E33: parsed from address | F33: =FALSE() -> FALSE | G33: Balranald Shire Council | H33: NRMA | I33: 1 | J33: AC | K33: 22 kW | L33: 22 | M33: =FALSE() -> FALSE | N33: Existing Destination Chargers | O33: -34.577619 | P33: 142.74619
A34: 33 | C34: 2090 Broke Rd, Pokolbin, 2320 | D34: 2320 | E34: parsed from address | F34: =FALSE() -> FALSE | G34: Cessnock City Council | H34: NRMA | I34: 4 | J34: DC | K34: 75 kW | L34: 75 | M34: =FALSE() -> FALSE | N34: Existing Fast Chargers | O34: -32.773429 | P34: 151.29827
A35: 34 | C35: 26 Neilly St, Walgett, NSW 2832 | D35: 2832 | E35: parsed from address | F35: =TRUE() -> TRUE | G35: Walgett Shire Council | H35: NRMA | I35: 2 | J35: DC | K35: 75 kW | L35: 75 | M35: =FALSE() -> FALSE | N35: TfNSW Regional | O35: -30.020699 | P35: 148.11771
A36: 35 | C36: 28 Auburn Street, Moree, NSW 2400 | D36: 2400 | E36: parsed from address | F36: =TRUE() -> TRUE | G36: Moree Plains Shire Council | H36: NRMA | I36: 2 | J36: DC | K36: 50 kW | L36: 50 | M36: =FALSE() -> FALSE | N36: TfNSW Regional | O36: -29.46194 | P36: 149.84066
A37: 36 | C37: 29 Perry St, Euston NSW 2737 | D37: 2737 | E37: parsed from address | F37: =FALSE() -> FALSE | G37: Balranald Shire Council | H37: NRMA | I37: 4 | J37: DC | K37: 175 kW | L37: 175 | M37: =FALSE() -> FALSE | N37: Fast Charging R1 | O37: -34.576596 | P37: 142.74282
A38: 37 | B38: Narrandera Park | C38: 29-55 Twynam St, Narrandera, 2700 | D38: 2700 | E38: parsed from address | F38: =FALSE() -> FALSE | G38: Narrandera Shire Council | H38: NRMA | I38: 4 | J38: DC | K38: 180 kW | L38: 180 | M38: =FALSE() -> FALSE | N38: Existing Fast Chargers | O38: -34.746498 | P38: 146.55008
A39: 38 | B39: Narrandera Park | C39: 29-55 Twynam St, Narrandera, 2700 | D39: 2700 | E39: parsed from address | F39: =FALSE() -> FALSE | G39: Narrandera Shire Council | H39: NRMA | I39: 2 | J39: DC | K39: 50 kW | L39: 50 | M39: =FALSE() -> FALSE | N39: Existing Fast Chargers | O39: -34.746497 | P39: 146.55008
A40: 39 | C40: 2A Beach Rd, Batemans Bay, 2536 | D40: 2536 | E40: parsed from address | F40: =FALSE() -> FALSE | G40: Eurobodalla Shire Council | H40: NRMA | I40: 2 | J40: DC | K40: 50 kW | L40: 50 | M40: =FALSE() -> FALSE | N40: Existing Fast Chargers | O40: -35.708512 | P40: 150.17539
A41: 40 | C41: 3 Broomfield St, Cobar, NSW 2835 | D41: 2835 | E41: parsed from address | F41: =TRUE() -> TRUE | G41: Cobar Shire Council | H41: NRMA | I41: 2 | J41: DC | K41: 50 kW | L41: 50 | M41: =FALSE() -> FALSE | N41: TfNSW Regional | O41: -31.498839 | P41: 145.83761
A42: 41 | B42: Nabiac Park | C42: 35 Nabiac Street, Nabiac NSW 2312 | D42: 2312 | E42: parsed from address | F42: =FALSE() -> FALSE | G42: Mid-Coast Council | H42: NRMA | I42: 2 | J42: DC | K42: 50 kW | L42: 50 | M42: =FALSE() -> FALSE | N42: Existing Fast Chargers | O42: -32.099071 | P42: 152.38157
A43: 42 | C43: 424 Hoxton Park Rd, Prestons, NSW, 2170 | D43: 2170 | E43: parsed from address | F43: =FALSE() -> FALSE | G43: Liverpool City Council | H43: NRMA | I43: 4 | J43: DC | K43: 175 kW | L43: 175 | M43: =FALSE() -> FALSE | N43: Fast Charging R1 | O43: -33.930467 | P43: 150.87502
A44: 43 | C44: 50 Bathurst St, Brewarrina, NSW 2839 | D44: 2839 | E44: parsed from address | F44: =TRUE() -> TRUE | G44: Brewarrina Shire Council | H44: NRMA | I44: 4 | J44: DC | K44: 75 kW | L44: 75 | M44: =FALSE() -> FALSE | N44: TfNSW Regional | O44: -29.960719 | P44: 146.85775
A45: 44 | C45: 50 Lowe St, Queanbeyan, 2620 | D45: 2620 | E45: parsed from address | F45: =FALSE() -> FALSE | G45: Queanbeyan-Palerang Regional Council | H45: NRMA | I45: 1 | J45: AC | K45: 22 kW | L45: 22 | M45: =FALSE() -> FALSE | N45: Existing Destination Chargers | O45: -35.354983 | P45: 149.23291
A46: 45 | C46: 528 John Oxley Dr, Thrumster, 2444 | D46: 2444 | E46: parsed from address | F46: =FALSE() -> FALSE | G46: Port Macquarie-Hastings Council | H46: NRMA | I46: 2 | J46: DC | K46: 50 kW | L46: 50 | M46: =FALSE() -> FALSE | N46: Existing Fast Chargers | O46: -31.457966 | P46: 152.82735
A47: 46 | C47: 6 Castlereagh St Gilgandra, NSW 2827 | D47: 2827 | E47: parsed from address | F47: =TRUE() -> TRUE | G47: Gilgandra Shire Council | H47: NRMA | I47: 4 | J47: DC | K47: 75 kW | L47: 75 | M47: =FALSE() -> FALSE | N47: TfNSW Regional | O47: -31.722391 | P47: 148.65714
A48: 47 | C48: 7 Tank St, Lithgow, 2790 | D48: 2790 | E48: parsed from address | F48: =FALSE() -> FALSE | G48: Lithgow Council, City of | H48: NRMA | I48: 4 | J48: DC | K48: 50 kW | L48: 50 | M48: =FALSE() -> FALSE | N48: Existing Fast Chargers | O48: -33.478006 | P48: 150.16112
A49: 48 | C49: 76 Cowper St, Wallsend, 2287 | D49: 2287 | E49: parsed from address | F49: =FALSE() -> FALSE | G49: Newcastle City Council | H49: NRMA | I49: 4 | J49: DC | K49: 50 kW | L49: 50 | M49: =FALSE() -> FALSE | N49: Existing Fast Chargers | O49: -32.902721 | P49: 151.66977
A50: 49 | C50: 77 Darling St, Cowra, 2794 | D50: 2794 | E50: parsed from address | F50: =FALSE() -> FALSE | G50: Cowra Shire Council | H50: NRMA | I50: 2 | J50: DC | K50: 50 kW | L50: 50 | M50: =FALSE() -> FALSE | N50: Existing Fast Chargers | O50: -33.834112 | P50: 148.6944
A51: 50 | C51: 8 Stanley St, Bathurst, 2795 | D51: 2795 | E51: parsed from address | F51: =FALSE() -> FALSE | G51: Bathurst Regional Council | H51: NRMA | I51: 1 | J51: AC | K51: 22 kW | L51: 22 | M51: =FALSE() -> FALSE | N51: Existing Destination Chargers | O51: -33.413357 | P51: 149.58533
A52: 51 | C52: 8 Stanley St, Bathurst, NSW, 2795 | D52: 2795 | E52: parsed from address | F52: =FALSE() -> FALSE | G52: Bathurst Regional Council | H52: NRMA | I52: 4 | J52: DC | K52: 175 kW | L52: 175 | M52: =FALSE() -> FALSE | N52: Fast Charging R1 | O52: -33.413357 | P52: 149.58533
A53: 52 | C53: 8/24 Cross St, Wagga Wagga, NSW 2650 | D53: 2650 | E53: parsed from address | F53: =TRUE() -> TRUE | G53: Wagga Wagga City Council | H53: NRMA | I53: 2 | J53: DC | K53: 50 kW | L53: 50 | M53: =FALSE() -> FALSE | N53: TfNSW Regional | O53: -35.108358 | P53: 147.37355
A54: 53 | C54: 80 Little Barber St, Gunnedah, 2380 | D54: 2380 | E54: parsed from address | F54: =FALSE() -> FALSE | G54: Gunnedah Shire Council | H54: NRMA | I54: 2 | J54: DC | K54: 50 kW | L54: 50 | M54: =FALSE() -> FALSE | N54: Existing Fast Chargers | O54: -30.978145 | P54: 150.25099
A55: 54 | C55: 81 Hickory St, Dorrigo, NSW 2453 | D55: 2453 | E55: parsed from address | F55: =TRUE() -> TRUE | G55: Bellingen Shire Council | H55: NRMA | I55: 4 | J55: DC | K55: 75 kW | L55: 75 | M55: =FALSE() -> FALSE | N55: TfNSW Regional | O55: -30.338496 | P55: 152.71278
A56: 55 | C56: 81 Meehan St, Yass NSW 2582 | D56: 2582 | E56: parsed from address | F56: =TRUE() -> TRUE | G56: Yass Valley Council | H56: NRMA | I56: 2 | J56: DC | K56: 50 kW | L56: 50 | M56: =FALSE() -> FALSE | N56: TfNSW Regional | O56: -34.841228 | P56: 148.91249
A57: 56 | C57: 82 Marsh St, Armidale, NSW 2350 | D57: 2350 | E57: parsed from address | F57: =TRUE() -> TRUE | G57: Armidale Regional Council | H57: NRMA | I57: 2 | J57: DC | K57: 50 kW | L57: 50 | M57: =FALSE() -> FALSE | N57: TfNSW Regional | O57: -30.511924 | P57: 151.66967
A58: 57 | C58: 82 Mulgoa Rd, Jamisontown NSW 2750 | D58: 2750 | E58: parsed from address | F58: =FALSE() -> FALSE | H58: NRMA | I58: 4 | J58: Upcoming | K58: 2x350kW & 2x175kW | L58: 350 | M58: =TRUE() -> TRUE | O58: -33.764666 | P58: 150.68243
A59: 58 | C59: 89 Barwan St, Narrabri, NSW 2390, Australia, | D59: 2390 | E59: parsed from address | F59: =TRUE() -> TRUE | G59: Narrabri Shire Council | H59: NRMA | I59: 4 | J59: DC | K59: 50 kW | L59: 50 | M59: =FALSE() -> FALSE | N59: TfNSW Regional | O59: -30.325089 | P59: 149.7839
A60: 59 | C60: 89 Market St, Balranald, 2715 | D60: 2715 | E60: parsed from address | F60: =FALSE() -> FALSE | G60: Balranald Shire Council | H60: NRMA | I60: 2 | J60: DC | K60: 50 kW | L60: 50 | M60: =FALSE() -> FALSE | N60: Existing Fast Chargers | O60: -34.639541 | P60: 143.56471
A61: 60 | C61: 9 Bessemer St, Mittagong, 2575 | D61: 2575 | E61: parsed from address | F61: =FALSE() -> FALSE | G61: Wingecarribee Shire Council | H61: NRMA | I61: 2 | J61: AC | K61: 20 kW | L61: 20 | M61: =FALSE() -> FALSE | N61: Existing Destination Chargers | O61: -34.450088 | P61: 150.44246
A62: 61 | C62: Cabarita Beach Bowls and Sports Club, Cabarita Beach NSW 2488 | D62: 2488 | E62: parsed from address | F62: =FALSE() -> FALSE | G62: Tweed Shire Council | H62: NRMA | I62: 4 | J62: DC | K62: 175 kW | L62: 175 | M62: =FALSE() -> FALSE | N62: Fast Charging R1 | O62: -28.33165 | P62: 153.56428
A63: 62 | C63: Cabarita Rd, Bogangar, 2488 | D63: 2488 | E63: parsed from address | F63: =FALSE() -> FALSE | G63: Tweed Shire Council | H63: NRMA | I63: 1 | J63: AC | K63: 22 kW | L63: 22 | M63: =FALSE() -> FALSE | N63: Existing Destination Chargers | O63: -28.331692 | P63: 153.56414
A64: 63 | C64: Car Park behind the Civic Centre, Orange, 2800 | D64: 2800 | E64: parsed from address | F64: =FALSE() -> FALSE | G64: Orange City Council | H64: NRMA | I64: 2 | J64: DC | K64: 50 kW | L64: 50 | M64: =FALSE() -> FALSE | N64: Existing Fast Chargers | O64: -33.281426 | P64: 149.10279
A65: 64 | C65: Car park, 51 Evans St (Victoria Park), Inverell, NSW 2360 | D65: 2360 | E65: parsed from address | F65: =TRUE() -> TRUE | G65: Inverell Shire Council | H65: NRMA | I65: 2 | J65: DC | K65: 75 kW | L65: 75 | M65: =FALSE() -> FALSE | N65: TfNSW Regional | O65: -29.774603 | P65: 151.11472
A66: 65 | C66: Car park, Little Hoskins St, Temora, NSW 2666 | D66: 2666 | E66: parsed from address | F66: =TRUE() -> TRUE | G66: Temora Shire Council | H66: NRMA | I66: 2 | J66: DC | K66: 50 kW | L66: 50 | M66: =FALSE() -> FALSE | N66: TfNSW Regional | O66: -34.446034 | P66: 147.53426
A67: 66 | C67: Commercial St, Walla Walla, 2659 | D67: 2659 | E67: parsed from address | F67: =FALSE() -> FALSE | G67: Greater Hume Shire Council | H67: NRMA | I67: 1 | J67: AC | K67: 22 kW | L67: 22 | M67: =FALSE() -> FALSE | N67: Existing Destination Chargers | O67: -35.764937 | P67: 146.90104
A68: 67 | C68: Coonabarabran Visitor Cntr, Coonabarabran, 2357 | D68: 2357 | E68: parsed from address | F68: =FALSE() -> FALSE | G68: Warrumbungle Shire Council | H68: NRMA | I68: 2 | J68: DC | K68: 50 kW | L68: 50 | M68: =FALSE() -> FALSE | N68: Existing Fast Chargers | O68: -31.2788 | P68: 149.27924
A69: 68 | C69: Corner of Snowy River Avenue and Kalkite St, Jindabyne, 2627 | D69: 2627 | E69: parsed from address | F69: =FALSE() -> FALSE | G69: Snowy Monaro Regional Council | H69: NRMA | I69: 4 | J69: DC | K69: 50 kW | L69: 50 | M69: =FALSE() -> FALSE | N69: Existing Fast Chargers | O69: -36.415952 | P69: 148.6198
A70: 69 | C70: Council Car Park Lot 4 / DP251076 between 46 Lowe Street Queanbeyan NSW 2620 | D70: 2620 | E70: parsed from address | F70: =FALSE() -> FALSE | G70: Queanbeyan-Palerang Regional Council | H70: NRMA | I70: 4 | J70: DC | K70: 175 kW | L70: 175 | M70: =FALSE() -> FALSE | N70: Fast Charging R1 | O70: -35.354983 | P70: 149.23291
A71: 70 | C71: 27 Dalton St, Parkes NSW 2870 | D71: 2870 | E71: parsed from address | F71: =FALSE() -> FALSE | G71: Parkes Shire Council | H71: NRMA | I71: 2 | J71: DC | K71: 75 kW | L71: 75 | M71: =FALSE() -> FALSE | N71: Existing Fast Chargers | O71: -33.137207 | P71: 148.17262
A72: 71 | C72: 14 Darling Dr, Sydney NSW 2000 | D72: 2000 | E72: parsed from address | F72: =FALSE() -> FALSE | G72: Sydney, Council of the City of | H72: NRMA | I72: 20 | J72: AC | K72: 22 kW | L72: 22 | M72: =FALSE() -> FALSE | N72: Existing Destination Chargers | O72: -33.87515 | P72: 151.19956
A73: 72 | C73: 14 Darling Dr, Sydney NSW 2000 | D73: 2000 | E73: parsed from address | F73: =FALSE() -> FALSE | G73: Sydney, Council of the City of | H73: NRMA | I73: 5 | J73: AC | K73: 22 kW | L73: 22 | M73: =FALSE() -> FALSE | N73: Existing Destination Chargers | O73: -33.876752 | P73: 151.20002
A74: 73 | C74: 52B Eskbank St, Lithgow NSW 2790 | D74: 2790 | E74: parsed from address | F74: =FALSE() -> FALSE | G74: Lithgow Council, City of | H74: NRMA | I74: 4 | J74: DC | K74: 180 kW | L74: 180 | M74: =FALSE() -> FALSE | N74: Existing Fast Chargers | O74: -33.481238 | P74: 150.1588
A75: 74 | C75: Gasworks Ln, Molong, 2866 | D75: 2866 | E75: parsed from address | F75: =FALSE() -> FALSE | G75: Cabonne Council | H75: NRMA | I75: 1 | J75: AC | K75: 22 kW | L75: 22 | M75: =FALSE() -> FALSE | N75: Existing Destination Chargers | O75: -33.090899 | P75: 148.87041
A76: 75 | C76: Gasworks Ln, Molong, NSW, 2866 | D76: 2866 | E76: parsed from address | F76: =FALSE() -> FALSE | G76: Cabonne Council | H76: NRMA | I76: 4 | J76: DC | K76: 175 kW | L76: 175 | M76: =FALSE() -> FALSE | N76: Fast Charging R1 | O76: -33.091201 | P76: 148.87066
A77: 76 | C77: 81 Gipps St, Bega NSW 2550 | D77: 2550 | E77: parsed from address | F77: =FALSE() -> FALSE | G77: Bega Valley Shire Council | H77: NRMA | I77: 2 | J77: DC | K77: 50 kW | L77: 50 | M77: =FALSE() -> FALSE | N77: Existing Fast Chargers | O77: -36.673247 | P77: 149.84305
A78: 77 | C78: 42 Hastings St, Wauchope NSW 2446 | D78: 2446 | E78: parsed from address | F78: =FALSE() -> FALSE | G78: Port Macquarie-Hastings Council | H78: NRMA | I78: 4 | J78: DC | K78: 60 kW | L78: 60 | M78: =FALSE() -> FALSE | N78: Existing Fast Chargers | O78: -31.456154 | P78: 152.73272
... A81: 80 | C81: 441 Kiewa St, Albury NSW 2640 | D81: 2640 | E81: parsed from address | F81: =FALSE() -> FALSE | G81: Albury City Council | H81: NRMA | I81: 2 | J81: DC | K81: 50 kW | L81: 50 | M81: =FALSE() -> FALSE | N81: Existing Fast Chargers | O81: -36.083792 | P81: 146.91483
A82: 81 | C82: 51 Bromide St, Broken Hill NSW 2880 | D82: 2880 | E82: parsed from address | F82: =TRUE() -> TRUE | G82: Broken Hill City Council | H82: NRMA | I82: 2 | J82: DC | K82: 50 kW | L82: 50 | M82: =FALSE() -> FALSE | N82: TfNSW Regional | O82: -31.959618 | P82: 141.45957
A83: 82 | B83: Club Mudgee Car Park | C83: 99 Mortimer St, Mudgee NSW 2850 | D83: 2850 | E83: parsed from address | F83: =FALSE() -> FALSE | G83: Mid-Western Regional Council | H83: NRMA | I83: 2 | J83: DC | K83: 50 kW | L83: 50 | M83: =FALSE() -> FALSE | N83: Existing Fast Chargers | O83: -32.593681 | P83: 149.58626
A84: 83 | B84: Sydney Olympic Park | C84: 9 Murray Rose Ave, Sydney Olympic Park NSW 2127 | D84: 2127 | E84: parsed from address | F84: =FALSE() -> FALSE | G84: Parramatta, Council of the City of | H84: NRMA | I84: 2 | J84: DC | K84: 50 kW | L84: 50 | M84: =FALSE() -> FALSE | N84: Existing Fast Chargers | O84: -33.846038 | P84: 151.06981
A85: 84 | C85: 7 Prospect St, Holbrook NSW 2644 | D85: 2644 | E85: parsed from address | F85: =FALSE() -> FALSE | G85: Greater Hume Shire Council | H85: NRMA | I85: 2 | J85: DC | K85: 50 kW | L85: 50 | M85: =FALSE() -> FALSE | N85: Existing Fast Chargers | O85: -35.717574 | P85: 147.31777
A86: 85 | B86: Jugiong Playground & Swimming Pool | C86: 319 Riverside Dr, Jugiong NSW 2726 | D86: 2726 | E86: parsed from address | F86: =FALSE() -> FALSE | G86: Hilltops Council | H86: NRMA | I86: 2 | J86: DC | K86: 50 kW | L86: 50 | M86: =FALSE() -> FALSE | N86: Existing Fast Chargers | O86: -34.823429 | P86: 148.3257
A87: 86 | B87: Lovell St Car Park | C87: 88 Lovell St, Young NSW 2594 | D87: 2594 | E87: parsed from address | F87: =FALSE() -> FALSE | G87: Hilltops Council | H87: NRMA | I87: 2 | J87: DC | K87: 50 kW | L87: 50 | M87: =FALSE() -> FALSE | N87: Existing Fast Chargers | O87: -34.311774 | P87: 148.2951
A88: 87 | B88: Shire St Parking | C88: 13-15 Shire St, West Wyalong NSW 2671 | D88: 2671 | E88: parsed from address | F88: =FALSE() -> FALSE | G88: Bland Shire Council | H88: NRMA | I88: 2 | J88: DC | K88: 50 kW | L88: 50 | M88: =FALSE() -> FALSE | N88: Existing Fast Chargers | O88: -33.923822 | P88: 147.20338
A89: 88 | C89: 47 Short St, Mudgee NSW 2850 | D89: 2850 | E89: parsed from address | F89: =FALSE() -> FALSE | G89: Mid-Western Regional Council | H89: NRMA | I89: 4 | J89: DC | K89: 125 kW | L89: 125 | M89: =FALSE() -> FALSE | N89: Existing Fast Chargers | O89: -32.58961 | P89: 149.58576
A90: 89 | B90: Skillman's Lane Car Park | C90: Skillman's Lane, Coonamble, NSW 2829 | D90: 2829 | E90: parsed from address | F90: =TRUE() -> TRUE | G90: Coonamble Shire Council | H90: NRMA | I90: 4 | J90: DC | K90: 50 kW | L90: 50 | M90: =FALSE() -> FALSE | N90: TfNSW Regional | O90: -30.95278 | P90: 148.38791
A91: 90 | B91: Glen Innes Town Hall | C91: Sommerlad Ln, Glen Innes, 2370 | D91: 2370 | E91: parsed from address | F91: =FALSE() -> FALSE | G91: Glen Innes Severn Council | H91: NRMA | I91: 2 | J91: DC | K91: 50 kW | L91: 50 | M91: =FALSE() -> FALSE | N91: Existing Fast Chargers | O91: -29.738464 | P91: 151.73631
A92: 91 | B92: Batemans Bay Regional Arts Aquatic & Leisure Centre | C92: 12 Vesper St, Batemans Bay NSW 2536 | D92: 2536 | E92: parsed from address | F92: =FALSE() -> FALSE | G92: Eurobodalla Shire Council | H92: NRMA | I92: 4 | J92: DC | K92: 75 kW | L92: 75 | M92: =FALSE() -> FALSE | N92: Existing Fast Chargers | O92: -35.709553 | P92: 150.17398
A93: 92 | B93: Walton Lane Car Park | C93: 5 Walton Lane, Picton NSW 2571 | D93: 2571 | E93: parsed from address | F93: =FALSE() -> FALSE | G93: Wollondilly Shire Council | H93: NRMA | I93: 2 | J93: DC | K93: 50 kW | L93: 50 | M93: =FALSE() -> FALSE | N93: Existing Fast Chargers | O93: -34.168288 | P93: 150.61094
A94: 93 | B94: Western Plains Cultural Centre | C94: 76 Wingewarra St, Dubbo NSW 2830 | D94: 2830 | E94: parsed from address | F94: =FALSE() -> FALSE | G94: Dubbo Regional Council | H94: NRMA | I94: 2 | J94: DC | K94: 50 kW | L94: 50 | M94: =FALSE() -> FALSE | N94: Existing Fast Chargers | O94: -32.249363 | P94: 148.60919
A95: 94 | C95: , Muswellbrook, 2333 | D95: 2333 | E95: parsed from address | F95: =FALSE() -> FALSE | G95: Muswellbrook Shire Council | H95: EVUp | I95: 2 | J95: AC | K95: 22 kW | L95: 22 | M95: =FALSE() -> FALSE | N95: Existing Destination Chargers | O95: -32.262242 | P95: 150.89014
A96: 95 | C96: 01 Wallgrove Road, Sydney, 2766 | D96: 2766 | E96: parsed from address | F96: =FALSE() -> FALSE | G96: Blacktown City Council | H96: BP | I96: 4 | J96: DC | K96: 150 kW | L96: 150 | M96: =FALSE() -> FALSE | N96: Existing Fast Chargers | O96: -33.811004 | P96: 150.8496
A97: 96 | C97: 1 Balfour St, Sydney, 2070 | D97: 2070 | E97: parsed from address | F97: =FALSE() -> FALSE | G97: Ku-ring-gai Council | H97: Chargefox | I97: 7 | J97: AC | K97: 22 kW | L97: 22 | M97: =FALSE() -> FALSE | N97: Existing Destination Chargers | O97: -33.774101 | P97: 151.16703
A98: 97 | C98: 1 Bay Ln, Byron Bay, 2481 | D98: 2481 | E98: parsed from address | F98: =FALSE() -> FALSE | G98: Byron Shire Council | H98: Tesla | I98: 2 | J98: AC | K98: 19 kW | L98: 19 | M98: =FALSE() -> FALSE | N98: Existing Destination Chargers | O98: -28.641819 | P98: 153.61363
A99: 98 | C99: 1 Bay St, Sydney, 2037 | D99: 2037 | E99: parsed from address | F99: =FALSE() -> FALSE | G99: Sydney, Council of the City of | H99: Tesla | I99: 16 | J99: DC | K99: 130 kW | L99: 130 | M99: =FALSE() -> FALSE | N99: Existing Fast Chargers | O99: -33.883504 | P99: 151.19443
A100: 99 | C100: 1 Bells Blvd, Kingscliff, 2487 | D100: 2487 | E100: parsed from address | F100: =FALSE() -> FALSE | G100: Tweed Shire Council | H100: Evie | I100: 4 | J100: DC | K100: 75 kW | L100: 75 | M100: =FALSE() -> FALSE | N100: Existing Fast Chargers | O100: -28.276903 | P100: 153.57708
A101: 100 | C101: 1 Bradleys Head Rd, Sydney, 2088 | D101: 2088 | E101: parsed from address | F101: =FALSE() -> FALSE | G101: Mosman Municipal Council | H101: Chargefox | I101: 1 | J101: AC | K101: 22 kW | L101: 22 | M101: =FALSE() -> FALSE | N101: Existing Destination Chargers | O101: -33.841037 | P101: 151.24224
A102: 101 | C102: 1 Bradleys Head Rd, Sydney, 2088 | D102: 2088 | E102: parsed from address | F102: =FALSE() -> FALSE | G102: Mosman Municipal Council | H102: Chargefox | I102: 1 | J102: AC | K102: 22 kW | L102: 22 | M102: =FALSE() -> FALSE | N102: Existing Destination Chargers | O102: -33.841418 | P102: 151.24263
A103: 102 | C103: 1 Cathedral Sq, Sydney, 2000 | D103: 2000 | E103: parsed from address | F103: =FALSE() -> FALSE | G103: Sydney, Council of the City of | H103: AXCharge | I103: 3 | J103: AC | K103: 22 kW | L103: 22 | M103: =FALSE() -> FALSE | N103: Existing Destination Chargers | O103: -33.871368 | P103: 151.21374
A104: 103 | C104: 1 Dalgal Way, Sydney, 2037 | D104: 2037 | E104: parsed from address | F104: =FALSE() -> FALSE | G104: Sydney, Council of the City of | H104: Tesla | I104: 2 | J104: AC | K104: 22 kW | L104: 22 | M104: =FALSE() -> FALSE | N104: Existing Destination Chargers | O104: -33.876374 | P104: 151.17764
...

Sheet Transport_Stops
A1: LOCATION_NAME | B1: TSN | C1: EFA_ID | D1: ADDRESS | E1: Postcode | F1: Postcode_source | G1: TRANSPORT_MODE | H1: FACILITIES | I1: ACCESSIBILITY | J1: PHONE | K1: MORNING_PEAK | L1: AFTERNOON_PEAK | M1: SHORT_PLATFORM | N1: LATITUDE | O1: LONGITUDE
A2: Abbotsford Wharf | B2: 2046158 | C2: 10102011 | D2: Great North Rd, Abbotsford NSW 2046 | E2: 2046 | F2: parsed from address | G2: Bus, Ferry | H2: Kiss and ride stopping area | Bike racks | Toilets | Emergency help point | Next service display | I2: This location is Independent Access | Wheelchair ramp boarding assistance | Hearing loop | PA system for announcements | Wharf edge tactiles | M2: =FALSE() -> FALSE | N2: -33.843674 | O2: 151.12817
A3: Aberdeen Station | B3: 233610 | C3: 10101192 | D3: Macqueen St, Aberdeen NSW 2336 | E3: 2336 | F3: parsed from address | G3: Train, Bus, Coach | H3: Commuter car park | Emergency help point | No Opal card top up or single trip ticket sales | I3: This location is Independent Access | Wheelchair ramp boarding assistance | Hearing loop | PA system for announcements | Platform edge tactiles | Stairs | J3: 02 6543 1018 | K3: 6am-10am | L3: 3pm-7pm | M3: =TRUE() -> TRUE | N3: -32.167104 | O3: 150.89205
A4: Adamstown Station | B4: 228920 | C4: 10101159 | D4: Park Ave, Adamstown NSW 2289 | E4: 2289 | F4: parsed from address | G4: Train, Bus | H4: Commuter car park | Wheelchair accessible car space | Kiss and ride stopping area | Bike racks | Emergency help point | Information point | Payphone | No Opal card top up or single trip ticket sales | I4: This location is Independent Access | Wheelchair ramp boarding assistance | Hearing loop | PA system for announcements | Platform edge tactiles | Level crossing | Stairs | Lift | J4: 02 4962 9295 | K4: 6am-10am | L4: 3pm-7pm | M4: =TRUE() -> TRUE | N4: -32.93373 | O4: 151.72008
A5: Adelaide Central Bus Station | B5: 50001 | C5: 10102932 | D5: Franklin St, Adelaide SA 5000 | E5: 5000 | F5: parsed from address | G5: Coach | I5: This location is Not Accessible | | M5: =FALSE() -> FALSE | N5: -34.92748 | O5: 138.5955
A6: Adelong Coach Stop | B6: 272919 | C6: 10102814 | D6: Neill St at Tumut St, Adelong NSW 2729 | E6: 2729 | F6: parsed from address | G6: Coach | I6: This location is Not Accessible | | M6: =FALSE() -> FALSE | N6: -35.308251 | O6: 148.0635
A7: Albion Park Station | B7: 252710 | C7: 10101381 | D7: Princes Hwy, Albion Park Rail NSW 2527 | E7: 2527 | F7: parsed from address | G7: Train, Bus | H7: Commuter car park | Wheelchair accessible car space | Kiss and ride stopping area | Bike racks | Toilets | Wheelchair accessible toilet | Baby change table | Emergency help point | Payphone | Opal card top up or single trip ticket machine (Card Payment only) | I7: This location is Assisted Access | Wheelchair ramp boarding assistance | PA system for announcements | Platform edge tactiles | Level crossing | Stairs | J7: 02 4223 5416 | K7: 6am-10am | L7: 3pm-7pm | M7: =TRUE() -> TRUE | N7: -34.562647 | O7: 150.7985
A8: Albury Station | B8: 26401 | C8: 10101849 | D8: Railway Pl, East Albury NSW 2640 | E8: 2640 | F8: parsed from address | G8: Train, Coach, Taxi | H8: Commuter car park | Wheelchair accessible car space | Kiss and ride stopping area | Taxi rank | Bike racks | Toilets | Wheelchair accessible toilet | Baby change table | Emergency help point | Information point | Payphone | Next service display | I8: This location is Independent Access | Wheelchair ramp boarding assistance | Hearing loop | Hearing loop (ticket counter) | PA system for announcements | Platform edge tactiles | Stairs | M8: =FALSE() -> FALSE | N8: -36.084068 | O8: 146.92469
A9: Alectown Coach Stop | B9: 2870731 | C9: 10102823 | D9: Goobang St before Cross St, Alectown NSW 2870 | E9: 2870 | F9: parsed from address | G9: Coach | I9: This location is Not Accessible | | M9: =FALSE() -> FALSE | N9: -32.933121 | O9: 148.24023
A10: Allawah Station | B10: 222020 | C10: 10101338 | D10: Railway Pde, Allawah NSW 2218 | E10: 2218 | F10: parsed from address | G10: Train, Bus | H10: Commuter car park | Wheelchair accessible car space | Kiss and ride stopping area | Bike racks | Toilets | Wheelchair accessible toilet | Baby change table | Emergency help point | Payphone | Next service display | Opal card top up or single trip ticket machine (Cash or Card Payment) | I10: This location is Independent Access | Wheelchair ramp boarding assistance | Hearing loop | PA system for announcements | Platform edge tactiles | Stairs | Lift | J10: 02 9563 7415 | K10: 6am-10am | L10: 3pm-7pm | M10: =FALSE() -> FALSE | N10: -33.969584 | O10: 151.11433
A11: Allworth Coach Stop | B11: 2425101 | C11: 10102780 | D11: The Bucketts Way opp Allworth Rd, Allworth NSW 2425 | E11: 2425 | F11: parsed from address | G11: Coach | I11: This location is Not Accessible | | M11: =FALSE() -> FALSE | N11: -32.531345 | O11: 151.9442
A12: Alstonville Coach Stop | B12: 2477393 | C12: 10102751 | D12: Main St at Daley St, Alstonville NSW 2477 | E12: 2477 | F12: parsed from address | G12: Coach | I12: This location is Not Accessible | | M12: =FALSE() -> FALSE | N12: -28.8418 | O12: 153.44001
A13: Ardlethan Coach Stop | B13: 266590 | C13: 10102847 | D13: Ariah St before Yithan St, Ardlethan NSW 2665 | E13: 2665 | F13: parsed from address | G13: Coach | I13: This location is Not Accessible | | M13: =FALSE() -> FALSE | N13: -34.357807 | O13: 146.90256
A14: Ariah Park Coach Stop | B14: 266591 | C14: 10102849 | D14: Ariah Park Post Office, Coolamon St, Ariah Park NSW 2665 | E14: 2665 | F14: parsed from address | G14: Coach | I14: This location is Not Accessible | | M14: =FALSE() -> FALSE | N14: -34.347706 | O14: 147.22108
A15: Arlington Light Rail | B15: 220322 | C15: 10101623 | D15: Constitution Rd, Dulwich Hill NSW 2203 | E15: 2203 | F15: parsed from address | G15: Light rail | H15: Kiss and ride stopping area | Bike racks | Emergency help point | I15: This location is Independent Access | Hearing loop | PA system for announcements | Platform edge tactiles | Level crossing | Stairs | K15: 6.30am-10am | L15: 3pm-7pm | M15: =FALSE() -> FALSE | N15: -33.901841 | O15: 151.13806
A16: Armidale Station | B16: 23501 | C16: 10101819 | D16: Brown St, Armidale NSW 2350 | E16: 2350 | F16: parsed from address | G16: Train, Coach, Taxi | H16: Commuter car park | Wheelchair accessible car space | Kiss and ride stopping area | Taxi rank | Bike racks | Toilets | Wheelchair accessible toilet | Baby change table | Emergency help point | Information point | Next service display | I16: This location is Independent Access | Wheelchair ramp boarding assistance | Hearing loop | PA system for announcements | Platform edge tactiles | Stairs | M16: =FALSE() -> FALSE | N16: -30.515373 | O16: 151.65175
A17: Armidale Town Coach Stop | B17: 2350869 | C17: 10102867 | D17: Central Beardy Mall, Faulkner St, Armidale NSW 2350 | E17: 2350 | F17: parsed from address | G17: Coach | I17: This location is Not Accessible | | M17: =FALSE() -> FALSE | N17: -30.513408 | O17: 151.66715
A18: Arncliffe Station | B18: 220520 | C18: 10101333 | D18: Firth St, Arncliffe NSW 2205 | E18: 2205 | F18: parsed from address | G18: Train, Bus, Taxi | H18: Commuter car park | Wheelchair accessible car space | Kiss and ride stopping area | Taxi rank | Bike racks | Toilets | Wheelchair accessible toilet | Baby change table | Emergency help point | Payphone | Next service display | Opal card top up or single trip ticket machine (Card Payment only) | I18: This location is Independent Access | Wheelchair ramp boarding assistance | Hearing loop | PA system for announcements | Platform edge tactiles | Stairs | Lift | J18: 02 9563 7431 | K18: 6.30am-10am | L18: 3pm-7pm | M18: =FALSE() -> FALSE | N18: -33.936456 | O18: 151.1473
A19: Artarmon Station | B19: 206410 | C19: 10101116 | D19: Hampden Rd, Artarmon NSW 2064 | E19: 2064 | F19: parsed from address | G19: Train, Taxi | H19: Wheelchair accessible car space | Kiss and ride stopping area | Taxi rank | Bike racks | Bike lockers | Wheelchair accessible toilet | Baby change table | Emergency help point | Payphone | Next service display | Opal card top up or single trip ticket machine (Card Payment only) | I19: This location is Independent Access | Wheelchair ramp boarding assistance | Hearing loop | PA system for announcements | Platform edge tactiles | Stairs | Lift | J19: 02 9379 1140 | K19: 6.30am-10am | L19: 3pm-7pm | M19: =TRUE() -> TRUE | N19: -33.808903 | O19: 151.18529
A20: Ashfield Station | B20: 213110 | C20: 10101209 | D20: Brown St, Ashfield NSW 2131 | E20: 2131 | F20: parsed from address | G20: Train, Bus, Taxi | H20: Commuter car park | Transport Park&Ride | Wheelchair accessible car space | Kiss and ride stopping area | Taxi rank | Bike racks | Bike lockers | Bike shed | Toilets | Wheelchair accessible toilet (MLAK) | Baby change table | Emergency help point | Payphone | Next service display | Opal card top up or single trip ticket machine (Card Payment only) | Opal card top up machine (Card Payment only) | I20: This location is Independent Access | Wheelchair ramp boarding assistance | Hearing loop | PA system for announcements | Platform edge tactiles | Stairs | Lift | J20: 02 9752 8356 | K20: 6.30am-10am | L20: 3pm-7pm | M20: =FALSE() -> FALSE | N20: -33.887551 | O20: 151.1255
A21: Asquith Station | B21: 207730 | C21: 10101128 | D21: Haldane St, Asquith NSW 2077 | E21: 2077 | F21: parsed from address | G21: Train | H21: Commuter car park | Wheelchair accessible car space | Kiss and ride stopping area | Toilets | Emergency help point | Payphone | Next service display | Opal card top up or single trip ticket machine (Card Payment only) | I21: This location is Assisted Access | Wheelchair ramp boarding assistance | Hearing loop | PA system for announcements | Platform edge tactiles | J21: 02 9847 8495 | K21: 6.30am-10am | L21: 3pm-7pm | M21: =TRUE() -> TRUE | N21: -33.68877 | O21: 151.10803
A22: Attunga Coach Stop | B22: 234523 | C22: 10102700 | D22: Fossickers Way at Ridge St, Attunga NSW 2345 | E22: 2345 | F22: parsed from address | G22: Coach | I22: This location is Not Accessible | | M22: =FALSE() -> FALSE | N22: -30.92869 | O22: 150.84584
A23: Auburn Station | B23: 214410 | C23: 10101219 | D23: Rawson St, Auburn NSW 2144 | E23: 2144 | F23: parsed from address | G23: Train, Bus, Taxi | H23: Wheelchair accessible car space | Kiss and ride stopping area | Taxi rank | Bike racks | Bike lockers | Toilets | Wheelchair accessible toilet (MLAK) | Baby change table | Emergency help point | Payphone | Next service display | Opal card top up or single trip ticket machine (Card Payment only) | Opal card top up machine (Card Payment only) | I23: This location is Independent Access | Wheelchair ramp boarding assistance | Hearing loop | PA system for announcements | Platform edge tactiles | Stairs | Lift | J23: 02 9848 9206 | K23: 6.30am-10am | L23: 3pm-7pm | M23: =FALSE() -> FALSE | N23: -33.84927 | O23: 151.03287
A24: Austinmer Station | B24: 251540 | C24: 10101363 | D24: Railway Ave, Austinmer NSW 2515 | E24: 2515 | F24: parsed from address | G24: Train, Bus | H24: Commuter car park | Wheelchair accessible car space | Toilets | Emergency help point | Payphone | No Opal card top up or single trip ticket sales | I24: This location is Assisted Access | Wheelchair ramp boarding assistance | Hearing loop | PA system for announcements | Platform edge tactiles | J24: 02 4223 5573 | K24: 6.30am-10am | L24: 3pm-7pm | M24: =TRUE() -> TRUE | N24: -34.30641 | O24: 150.92931
A25: Awaba Station | B25: 228310 | C25: 10101150 | D25: Adelaide St, Awaba NSW 2283 | E25: 2283 | F25: parsed from address | G25: Train, Bus | H25: Commuter car park | Emergency help point | Information point | No Opal card top up or single trip ticket sales | I25: This location is Not Accessible | Wheelchair ramp boarding assistance | Hearing loop | PA system for announcements | Stairs | J25: 02 4349 9241 | K25: 6.30am-10am | L25: 3pm-7pm | M25: =TRUE() -> TRUE | N25: -33.01292 | O25: 151.54163
A26: Ballina Coach Stop | B26: 2478673 | C26: 10102749 | D26: Tamar St before Moon St, Ballina NSW 2478 | E26: 2478 | F26: parsed from address | G26: Bus, Coach | I26: This location is Not Accessible | | M26: =FALSE() -> FALSE | N26: -28.86933 | O26: 153.56059
A27: Ballina West Coach Stop | B27: 2478675 | C27: 10102750 | D27: West Tower Tavern, River St, West Ballina NSW 2478 | E27: 2478 | F27: parsed from address | G27: Bus, Coach | I27: This location is Not Accessible | | M27: =FALSE() -> FALSE | N27: -28.864101 | O27: 153.53393
A28: Balmain East Wharf | B28: 20414 | C28: 10102010 | D28: Darling St, Balmain East NSW 2041 | E28: 2041 | F28: parsed from address | G28: Bus, Ferry | H28: Emergency help point | Next service display | Opal card top up or single trip ticket machine (Card Payment only) | I28: This location is Independent Access | Wheelchair ramp boarding assistance | Hearing loop | PA system for announcements | Wharf edge tactiles | Stairs | M28: =FALSE() -> FALSE | N28: -33.856967 | O28: 151.19598
A29: Balmain West Wharf | B29: 204155 | C29: 10102006 | D29: Elliott St, Balmain West NSW 2041 | E29: 2041 | F29: parsed from address | G29: Ferry | H29: Toilets | Wheelchair accessible toilet | Emergency help point | Information point | Next service display | I29: This location is Assisted Access | Wheelchair ramp boarding assistance | Hearing loop | Wharf edge tactiles | M29: =FALSE() -> FALSE | N29: -33.855082 | O29: 151.16875
A30: Balmain Wharf | B30: 204157 | C30: 10102008 | D30: Thames St, Balmain NSW 2041 | E30: 2041 | F30: parsed from address | G30: Ferry | H30: Wheelchair accessible car space | Kiss and ride stopping area | Bike racks | Emergency help point | Next service display | Opal card top up or single trip ticket machine (Card Payment only) | I30: This location is Independent Access | Wheelchair ramp boarding assistance | Hearing loop | PA system for announcements | Wharf edge tactiles | M30: =FALSE() -> FALSE | N30: -33.854716 | O30: 151.18636
A31: Balranald Coach Stop | B31: 271512 | C31: 10102854 | D31: Balranald Information Centre, Market St, Balranald NSW 2715 | E31: 2715 | F31: parsed from address | G31: Coach | I31: This location is Not Accessible | | M31: =FALSE() -> FALSE | N31: -34.640572 | O31: 143.56464
A32: Bangalow Coach Stop | B32: 2479103 | C32: 10102740 | D32: Station St at Byron St, Bangalow NSW 2479 | E32: 2479 | F32: parsed from address | G32: Coach | I32: This location is Not Accessible | | M32: =FALSE() -> FALSE | N32: -28.686545 | O32: 153.5248
A33: Bank Street Light Rail | B33: 200952 | C33: 10101635 | D33: Miller St, Pyrmont NSW 2009 | E33: 2009 | F33: parsed from address | G33: Light rail | H33: Emergency help point | Opal card top up or single trip ticket machine (Card Payment only) | I33: This location is Independent Access | PA system for announcements | Platform edge tactiles | Level crossing | Stairs | Lift | K33: 6.30am-10am | L33: 3pm-7pm | M33: =FALSE() -> FALSE | N33: -33.870917 | O33: 151.19229
A34: Banksia Station | B34: 221610 | C34: 10101334 | D34: Hattersley St, Banksia NSW 2216 | E34: 2216 | F34: parsed from address | G34: Train, Bus, Taxi | H34: Wheelchair accessible car space | Kiss and ride stopping area | Taxi rank | Toilets | Wheelchair accessible toilet | Baby change table | Emergency help point | Next service display | Opal card top up or single trip ticket machine (Card Payment only) | I34: This location is Independent Access | Wheelchair ramp boarding assistance | Hearing loop | PA system for announcements | Platform edge tactiles | Stairs | Lift | J34: 02 9563 7429 | K34: 6.30am-10am | L34: 3pm-7pm | M34: =FALSE() -> FALSE | N34: -33.945286 | O34: 151.14043
A35: Bankstown Station | B35: 220010 | C35: 10101401 | D35: North Tce, Bankstown NSW 2200 | E35: 2200 | F35: parsed from address | G35: Train, Bus, Taxi | H35: Commuter car park | Wheelchair accessible car space | Kiss and ride stopping area | Taxi rank | Bike racks | Bike lockers | Toilets | Wheelchair accessible toilet | Baby change table | Emergency help point | Payphone | Next service display | Opal card top up or single trip ticket machine (Card Payment only) | Opal card top up machine (Card Payment only) | Free mobile phone charging | I35: This location is Independent Access | Wheelchair ramp boarding assistance | PA system for announcements | Platform edge tactiles | Stairs | Lift | J35: 02 9563 7160 | K35: 6.30am-10am | L35: 3pm-7pm | M35: =FALSE() -> FALSE | N35: -33.917865 | O35: 151.03469
A36: Baradine Coach Stop | B36: 239612 | C36: 10102664 | D36: Wellington St at Darling St, Baradine NSW 2396 | E36: 2396 | F36: parsed from address | G36: Coach | I36: This location is Not Accessible | | M36: =FALSE() -> FALSE | N36: -30.949333 | O36: 149.06651
A37: Barangaroo Station | B37: 200046 | C37: 10101513 | D37: Hickson Rd, Barangaroo NSW 2000 | E37: 2000 | F37: parsed from address | G37: Metro, Bus, Ferry, Taxi | H37: Bike shed | Bike racks | Kiss and ride stopping area | Opal card top up or single trip ticket machine (Card Payment only) | Wheelchair accessible toilet | Baby change table | Taxi rank | Emergency help point | Next service display | I37: This location is Independent Access | Lift | Escalator | Hearing loop | Wheelchair ramp boarding assistance | Platform edge tactiles | PA system for announcements | K37: 6.30am-10am | L37: 3.00-7pm | M37: =FALSE() -> FALSE | N37: -33.859163 | O37: 151.20255
A38: Barangaroo Wharf | B38: 2000441 | C38: 10102039 | D38: Wulugul Walk, Barangaroo NSW 2000 | E38: 2000 | F38: parsed from address | G38: Ferry | H38: Emergency help point | Next service display | Opal card top up or single trip ticket machine (Cash or Card Payment) | Opal card top up or single trip ticket machine (Card Payment only) | I38: This location is Independent Access | Wheelchair ramp boarding assistance | Hearing loop | PA system for announcements | Wharf edge tactiles | M38: =FALSE() -> FALSE | N38: -33.864377 | O38: 151.20059
A39: Bardwell Park Station | B39: 220710 | C39: 10101410 | D39: Hartill-Law Ave, Bardwell Park NSW 2207 | E39: 2207 | F39: parsed from address | G39: Train, Bus | H39: Commuter car park | Kiss and ride stopping area | Toilets | Wheelchair accessible toilet | Baby change table | Emergency help point | Next service display | Opal card top up or single trip ticket machine (Cash or Card Payment) | I39: This location is Independent Access | Wheelchair ramp boarding assistance | Hearing loop | PA system for announcements | Platform edge tactiles | Stairs | Lift | J39: 02 9563 7428 | K39: 6.30am-10am | L39: 3pm-7pm | M39: =FALSE() -> FALSE | N39: -33.931617 | O39: 151.12486
A40: Barellan Coach Stop | B40: 266592 | C40: 10102846 | D40: Burley Griffin Way before Myall St, Barellan NSW 2665 | E40: 2665 | F40: parsed from address | G40: Coach | I40: This location is Not Accessible | | M40: =FALSE() -> FALSE | N40: -34.284782 | O40: 146.57203
A41: Bargo Station | B41: 257420 | C41: 10101303 | D41: Hume Hwy, Bargo NSW 2574 | E41: 2574 | F41: parsed from address | G41: Train, Bus | H41: Commuter car park | Wheelchair accessible car space | Bike racks | Toilets | Emergency help point | No Opal card top up or single trip ticket sales | I41: This location is Assisted Access | Wheelchair ramp boarding assistance | Hearing loop | PA system for announcements | J41: 02 4684 1320 | K41: 6am-10am | L41: 3pm-7pm | M41: =TRUE() -> TRUE | N41: -34.291365 | O41: 150.58021
A42: Barmedman Coach Stop | B42: 266812 | C42: 10102625 | D42: Queen St after Star St, Barmedman NSW 2668 | E42: 2668 | F42: parsed from address | G42: Coach | I42: This location is Not Accessible | | M42: =FALSE() -> FALSE | N42: -34.143373 | O42: 147.38661
A43: Barooga Coach Stop | B43: 364414 | C43: 10102827 | D43: Vermont St at McFarland St, Barooga NSW 3644 | E43: 3644 | F43: parsed from address | G43: Coach | I43: This location is Not Accessible | | M43: =FALSE() -> FALSE | N43: -35.91225 | O43: 145.69018
A44: Barraba Coach Stop | B44: 234712 | C44: 10102697 | D44: Alice St before Queen St, Barraba NSW 2347 | E44: 2347 | F44: parsed from address | G44: Coach | I44: This location is Not Accessible | | M44: =FALSE() -> FALSE | N44: -30.380272 | O44: 150.60961
A45: Bathurst Station | B45: 279538 | C45: 10101281 | D45: Havannah St, Bathurst NSW 2795 | E45: 2795 | F45: parsed from address | G45: Train, Bus, Coach, Taxi | H45: Commuter car park | Wheelchair accessible car space | Kiss and ride stopping area | Taxi rank | Bike racks | Toilets | Wheelchair accessible toilet | Baby change table | Emergency help point | Information point | Payphone | Next service display | Opal card top up or single trip ticket machine (Card Payment only) | I45: This location is Independent Access | Wheelchair ramp boarding assistance | Hearing loop | PA system for announcements | J45: 13 22 32 | K45: 6am-10am | L45: 3pm-7pm | M45: =TRUE() -> TRUE | N45: -33.425627 | O45: 149.58322
A46: Batlow Coach Stop | B46: 273017 | C46: 10102816 | D46: Memorial Ave at Pioneer St, Batlow NSW 2730 | E46: 2730 | F46: parsed from address | G46: Coach | I46: This location is Not Accessible | | M46: =FALSE() -> FALSE | N46: -35.520277 | O46: 148.14722
A47: Beckom Coach Stop | B47: 266593 | C47: 10102848 | D47: Service Station, Newell Hwy, Beckom NSW 2665 | E47: 2665 | F47: parsed from address | G47: Coach | I47: This location is Not Accessible | | M47: =FALSE() -> FALSE | N47: -34.331341 | O47: 146.95848
A48: Beecroft Station | B48: 211910 | C48: 10101197 | D48: Wongala Cres, Beecroft NSW 2119 | E48: 2119 | F48: parsed from address | G48: Train, Bus, Taxi | H48: Commuter car park | Wheelchair accessible car space | Kiss and ride stopping area | Taxi rank | Bike racks | Bike lockers | Wheelchair accessible toilet | Baby change table | Emergency help point | Payphone | Next service display | Opal card top up or single trip ticket machine (Cash or Card Payment) | I48: This location is Independent Access | Wheelchair ramp boarding assistance | Hearing loop | PA system for announcements | Platform edge tactiles | Stairs | Lift | J48: 02 9847 8421 | K48: 6.30am-10am | L48: 3pm-7pm | M48: =FALSE() -> FALSE | N48: -33.749954 | O48: 151.0663
A49: Beenleigh Coach Stop | B49: 310035 | C49: 10102901 | D49: Beenleigh Station, Coach Terminal, Alamein St, Beenleigh QLD 4207 | E49: 4207 | F49: parsed from address | G49: Coach | I49: This location is Not Accessible | | M49: =FALSE() -> FALSE | N49: -27.717673 | O49: 153.20452
A50: Bega Coach Stop | B50: 2550748 | C50: 10102790 | D50: Church St at Carp St, Bega NSW 2550 | E50: 2550 | F50: parsed from address | G50: Bus, Coach | I50: This location is Not Accessible | | M50: =FALSE() -> FALSE | N50: -36.673857 | O50: 149.84219
A51: Belbora Coach Stop | B51: 242294 | C51: 10102772 | D51: 2767 The Bucketts Way, Belbora NSW 2422 | E51: 2422 | F51: parsed from address | G51: Coach | I51: This location is Not Accessible | | M51: =FALSE() -> FALSE | N51: -32.012693 | O51: 152.1785
A52: Belconnen Interchange | B52: 5511 | C52: 10102916 | D52: Cohen st, Belconnen ACT 2617 | E52: 2617 | F52: parsed from address | G52: Bus, Coach | I52: This location is Not Accessible | | M52: =FALSE() -> FALSE | N52: -35.23976 | O52: 149.06966
A53: Bell Station | B53: 278620 | C53: 10101272 | D53: Bells Line of Road, Bell NSW 2786 | E53: 2786 | F53: parsed from address | G53: Train | H53: Emergency help point | Information point | No Opal card top up or single trip ticket sales | I53: This location is Assisted Access | Wheelchair ramp boarding assistance | Hearing loop | PA system for announcements | Level crossing | Stairs | J53: 02 4787 8452 | K53: 6am-10am | L53: 3pm-7pm | M53: =TRUE() -> TRUE | N53: -33.505686 | O53: 150.27889
A54: Bella Vista Station | B54: 2153478 | C54: 10101503 | D54: Mawson Ave, Bella Vista NSW 2153 | E54: 2153 | F54: parsed from address | G54: Metro, Bus, Taxi | H54: Bike shed | Bike racks | Commuter car park | Kiss and ride stopping area | Taxi rank | Opal card top up or single trip ticket machine (Cash or Card Payment) | Toilets | Wheelchair accessible toilet | Emergency help point | Payphone | I54: This location is Independent Access | Lift | Escalator | Hearing loop | Wheelchair ramp boarding assistance | Platform edge tactiles | PA system for announcements | K54: 6.30am-10am | L54: 3pm-7pm | M54: =FALSE() -> FALSE | N54: -33.730592 | O54: 150.94402
A55: Bellambi Station | B55: 251810 | C55: 10101367 | D55: Bellambi Lane, Bellambi NSW 2518 | E55: 2518 | F55: parsed from address | G55: Train, Bus, Taxi | H55: Commuter car park | Wheelchair accessible car space | Kiss and ride stopping area | Bike racks | Toilets | Wheelchair accessible toilet | Baby change table | Emergency help point | Payphone | Next service display | No Opal card top up or single trip ticket sales | I55: This location is Independent Access | Wheelchair ramp boarding assistance | Hearing loop | PA system for announcements | Platform edge tactiles | Level crossing | J55: 02 4223 5579 | K55: 6am-10am | L55: 3pm-7pm | M55: =TRUE() -> TRUE | N55: -34.363318 | O55: 150.9099
A56: Bellata Coach Stop | B56: 239717 | C56: 10102690 | D56: Railway Pde opp Wilga St, Bellata NSW 2397 | E56: 2397 | F56: parsed from address | G56: Coach | I56: This location is Not Accessible | | M56: =FALSE() -> FALSE | N56: -29.917328 | O56: 149.79107
A57: Bellata Station | B57: 23971 | C57: 10101815 | D57: Newell Hwy, Bellata NSW 2397 | E57: 2397 | F57: parsed from address | G57: Train | I57: This location is Independent Access | Wheelchair ramp boarding assistance | Hearing loop | PA system for announcements | M57: =FALSE() -> FALSE | N57: -29.9183 | O57: 149.7905
A58: Belmore Station | B58: 219210 | C58: 10101397 | D58: Burwood Rd, Belmore NSW 2192 | E58: 2192 | F58: parsed from address | G58: Bus, Taxi | H58: Commuter car park | Wheelchair accessible car space | Kiss and ride stopping area | Taxi rank | Toilets | Wheelchair accessible toilet | Baby change table | Emergency help point | Payphone | Next service display | I58: This location is Independent Access | Wheelchair ramp boarding assistance | PA system for announcements | Platform edge tactiles | Stairs | Lift | J58: 02 9563 7578 | K58: 6.30am-10am | L58: 3pm-7pm | M58: =FALSE() -> FALSE | N58: -33.917218 | O58: 151.08873
A59: Bemboka Coach Stop | B59: 2550749 | C59: 10102791 | D59: General Store, Snowy Mountains Hwy, Bemboka NSW 2550 | E59: 2550 | F59: parsed from address | G59: Coach | I59: This location is Not Accessible | | M59: =FALSE() -> FALSE | N59: -36.627333 | O59: 149.56878
A60: Ben Bullen Coach Stop | B60: 2790175 | C60: 10102683 | D60: Castlereagh Hwy after Quarry Rd, Ben Bullen NSW 2790 | E60: 2790 | F60: parsed from address | G60: Coach | I60: This location is Not Accessible | | M60: =FALSE() -> FALSE | N60: -33.218809 | O60: 150.02141
A61: Benaud Oval Light Rail | B61: 2151155 | C61: 10101712 | D61: Cnr Church St & Factory St, Parramatta NSW 2151 | E61: 2151 | F61: parsed from address | G61: Light rail | H61: Bike racks | Kiss and ride stopping area | No Opal card top up or single trip ticket sales | Next service display | Emergency help point | I61: This location is Independent Access | Level crossing | Hearing loop | Platform edge tactiles | PA system for announcements | K61: 6.30am-10am | L61: 3pm-7pm | M61: =FALSE() -> FALSE | N61: -33.800814 | O61: 151.00456
A62: Bendemeer Coach Stop | B62: 235521 | C62: 10102714 | D62: Caroline St after Henry St, Bendemeer NSW 2355 | E62: 2355 | F62: parsed from address | G62: Bus, Coach | I62: This location is Not Accessible | | M62: =FALSE() -> FALSE | N62: -30.883473 | O62: 151.1548
A63: Bendick Murrell Coach Stop | B63: 280314 | C63: 10102820 | D63: Main St after Ewens St, Bendick Murrell NSW 2803 | E63: 2803 | F63: parsed from address | G63: Coach | I63: This location is Not Accessible | | M63: =FALSE() -> FALSE | N63: -34.159821 | O63: 148.4458
A64: Berala Station | B64: 214120 | C64: 10101390 | D64: Woodburn Rd, Berala NSW 2141 | E64: 2141 | F64: parsed from address | G64: Train, Bus, Taxi | H64: Commuter car park | Wheelchair accessible car space | Kiss and ride stopping area | Taxi rank | Bike racks | Wheelchair accessible toilet | Baby change table | Emergency help point | Payphone | Next service display | Opal card top up or single trip ticket machine (Cash or Card Payment) | I64: This location is Independent Access | Wheelchair ramp boarding assistance | Hearing loop | PA system for announcements | Platform edge tactiles | Stairs | Lift | J64: 02 9752 8813 | K64: 6.30am-10am | L64: 3pm-7pm | M64: =FALSE() -> FALSE | N64: -33.871836 | O64: 151.03244
A65: Beresfield Station | B65: 232230 | C65: 10101172 | D65: Addison St, Beresfield NSW 2322 | E65: 2322 | F65: parsed from address | G65: Train, Bus, Taxi | H65: Commuter car park | Wheelchair accessible car space | Toilets | Wheelchair accessible toilet | Baby change table | Emergency help point | Information point | Payphone | I65: This location is Independent Access | Wheelchair ramp boarding assistance | Hearing loop | PA system for announcements | Platform edge tactiles | Stairs | Lift | J65: 02 4962 9944 | K65: 6am-10am | L65: 3pm-7pm | M65: =TRUE() -> TRUE | N65: -32.798946 | O65: 151.65786
A66: Berowra Station | B66: 208110 | C66: 10101131 | D66: Pacific Hwy, Berowra NSW 2081 | E66: 2081 | F66: parsed from address | G66: Train, Bus | H66: Commuter car park | Wheelchair accessible car space | Bike racks | Bike lockers | Toilets | Wheelchair accessible toilet | Baby change table | Emergency help point | Payphone | Next service display | I66: This location is Independent Access | Wheelchair ramp boarding assistance | Hearing loop | PA system for announcements | Platform edge tactiles | Stairs | Lift | J66: 02 9847 8496 | K66: 6.30am-10am | L66: 3pm-7pm | M66: =TRUE() -> TRUE | N66: -33.623657 | O66: 151.15297
A67: Berridale Coach Stop | B67: 262835 | C67: 10102797 | D67: Berridale Inn, Jindabyne Rd, Berridale NSW 2628 | E67: 2628 | F67: parsed from address | G67: Coach | I67: This location is Not Accessible | | M67: =FALSE() -> FALSE | N67: -36.365118 | O67: 148.82788
A68: Berrigan Coach Stop | B68: 271215 | C68: 10102834 | D68: Jerilderie St after Carter St, Berrigan NSW 2712 | E68: 2712 | F68: parsed from address | G68: Coach | I68: This location is Not Accessible | | M68: =FALSE() -> FALSE | N68: -35.658002 | O68: 145.8122
A69: Berry Station | B69: 253510 | C69: 10101388 | D69: Station Rd, Berry NSW 2535 | E69: 2535 | F69: parsed from address | G69: Train, Bus, Taxi | H69: Commuter car park | Wheelchair accessible car space | Toilets | Wheelchair accessible toilet | Baby change table | Emergency help point | Payphone | No Opal card top up or single trip ticket sales | I69: This location is Independent Access | Wheelchair ramp boarding assistance | Hearing loop | PA system for announcements | Platform edge tactiles | J69: 02 4464 1022 | K69: 6am-10am | L69: 3pm-7pm | M69: =TRUE() -> TRUE | N69: -34.780333 | O69: 150.69697
A70: Beverly Hills Station | B70: 220910 | C70: 10101413 | D70: Morgan St, Beverly Hills NSW 2209 | E70: 2209 | F70: parsed from address | G70: Train, Bus, Taxi | H70: Commuter car park | Wheelchair accessible car space | Kiss and ride stopping area | Bike racks | Toilets | Wheelchair accessible toilet | Baby change table | Emergency help point | Payphone | Next service display | Opal card top up or single trip ticket machine (Card Payment only) | I70: This location is Independent Access | Wheelchair ramp boarding assistance | Hearing loop | PA system for announcements | Platform edge tactiles | Stairs | Lift | J70: 02 9563 7650 | K70: 6.30am-10am | L70: 3pm-7pm | M70: =FALSE() -> FALSE | N70: -33.948849 | O70: 151.08169
A71: Bexhill Coach Stop | B71: 24801092 | C71: 10102744 | D71: Bexhill School, Banglow Rd, Bexhill NSW 2480 | E71: 2480 | F71: parsed from address | G71: Coach | I71: This location is Not Accessible | | M71: =FALSE() -> FALSE | N71: -28.76554 | O71: 153.34515
A72: Bexley North Station | B72: 220720 | C72: 10101411 | D72: Kingsgrove Ave, Bexley North NSW 2207 | E72: 2207 | F72: parsed from address | G72: Train, Bus | H72: Commuter car park | Wheelchair accessible car space | Kiss and ride stopping area | Bike racks | Toilets | Wheelchair accessible toilet | Baby change table | Emergency help point | Next service display | Opal card top up or single trip ticket machine (Cash or Card Payment) | I72: This location is Independent Access | Wheelchair ramp boarding assistance | Hearing loop | PA system for announcements | Platform edge tactiles | Stairs | Lift | J72: 02 9563 7613 | K72: 6.30am-10am | L72: 3pm-7pm | M72: =FALSE() -> FALSE | N72: -33.937566 | O72: 151.1134
A73: Bibbenluke Coach Stop | B73: 263225 | C73: 10102794 | D73: Monaro Hwy opp Bukalong Siding Rd, Bibbenluke NSW 2632 | E73: 2632 | F73: parsed from address | G73: Coach | I73: This location is Not Accessible | | M73: =FALSE() -> FALSE | N73: -36.811109 | O73: 149.2809
A74: Billinudgel Coach Stop | B74: 248375 | C74: 10102735 | D74: Bonanza Dr opp Lucky Lane, Billinudgel NSW 2483 | E74: 2483 | F74: parsed from address | G74: Coach | I74: This location is Not Accessible | | M74: =FALSE() -> FALSE | N74: -28.505065 | O74: 153.52838
A75: Binalong Coach Stop | B75: 258417 | C75: 10102806 | D75: Stephens St before Monteagle St, Binalong NSW 2584 | E75: 2584 | F75: parsed from address | G75: Coach | I75: This location is Not Accessible | | M75: =FALSE() -> FALSE | N75: -34.672661 | O75: 148.62915
A76: Bingara Coach Stop | B76: 240412 | C76: 10102695 | D76: Cunningham St at Maitland St, Bingara NSW 2404 | E76: 2404 | F76: parsed from address | G76: Coach | I76: This location is Not Accessible | | M76: =FALSE() -> FALSE | N76: -29.868516 | O76: 150.57217
A77: Biniguy Coach Stop | B77: 23992 | C77: 10102692 | D77: Gwydir Hwy at Biniguy Ave, Biniguy NSW 2399 | E77: 2399 | F77: parsed from address | G77: Coach | I77: This location is Not Accessible | | M77: =FALSE() -> FALSE | N77: -29.536002 | O77: 150.20611
A78: Binna Burra Coach Stop | B78: 2479104 | C78: 10102741 | D78: Bangalow Rd before Friday Hut Rd, Binna Burra NSW 2479 | E78: 2479 | F78: parsed from address | G78: Bus, Coach | I78: This location is Not Accessible | | M78: =FALSE() -> FALSE | N78: -28.706562 | O78: 153.49734
A79: Binnaway Coach Stop | B79: 239512 | C79: 10102666 | D79: Binnaway Post Office, Bullinda St, Binnaway NSW 2395 | E79: 2395 | F79: parsed from address | G79: Coach | I79: This location is Not Accessible | | M79: =FALSE() -> FALSE | N79: -31.55185 | O79: 149.37865
A80: Binya Coach Stop | B80: 266594 | C80: 10102845 | D80: Binya Post Office, Francis St, Binya NSW 2665 | E80: 2665 | F80: parsed from address | G80: Coach | I80: This location is Not Accessible | | M80: =FALSE() -> FALSE | N80: -34.229159 | O80: 146.34439
A81: Birchgrove Wharf | B81: 204156 | C81: 10102007 | D81: Louisa Rd, Birchgrove NSW 2041 | E81: 2041 | F81: parsed from address | G81: Ferry | H81: Kiss and ride stopping area | Emergency help point | Next service display | No Opal card top up or single trip ticket sales | I81: This location is Not Accessible | Wheelchair ramp boarding assistance | Hearing loop | PA system for announcements | Wharf edge tactiles | Stairs | M81: =FALSE() -> FALSE | N81: -33.846456 | O81: 151.18634
A82: Birrong Station | B82: 214320 | C82: 10101403 | D82: Rodd St, Birrong NSW 2143 | E82: 2143 | F82: parsed from address | G82: Train | H82: Commuter car park | Wheelchair accessible car space | Kiss and ride stopping area | Toilets | Wheelchair accessible toilet | Emergency help point | Next service display | Opal card top up or single trip ticket machine (Card Payment only) | Baby change table | Bike racks | I82: This location is Independent Access | Wheelchair ramp boarding assistance | PA system for announcements | Platform edge tactiles | Stairs | Lift | Hearing loop | J82: 02 9379 7727 | K82: 6.30am-10am | L82: 3pm-7pm | M82: =FALSE() -> FALSE | N82: -33.893279 | O82: 151.02404
A83: Blackheath Station | B83: 278510 | C83: 10101270 | D83: Railway Pde, Blackheath NSW 2785 | E83: 2785 | F83: parsed from address | G83: Train, Bus, Taxi | H83: Commuter car park | Wheelchair accessible car space | Kiss and ride stopping area | Taxi rank | Bike racks | Bike lockers | Toilets | Wheelchair accessible toilet | Emergency help point | Payphone | Next service display | No Opal card top up or single trip ticket sales | I83: This location is Independent Access | Wheelchair ramp boarding assistance | Hearing loop | PA system for announcements | Platform edge tactiles | Stairs | Lift | J83: 02 4780 3992 | K83: 6am-10am | L83: 3pm-7pm | M83: =TRUE() -> TRUE | N83: -33.632881 | O83: 150.28435
A84: Blacktown Station | B84: 214810 | C84: 10101235 | D84: Main St, Blacktown NSW 2148 | E84: 2148 | F84: parsed from address | G84: Train, Bus, Taxi | H84: Commuter car park | Wheelchair accessible car space | Kiss and ride stopping area | Taxi rank | Bike racks | Bike lockers | Bike shed | Toilets | Wheelchair accessible toilet | Baby change table | Emergency help point | Payphone | Next service display | Opal card top up or single trip ticket machine (Card Payment only) | Opal card top up machine (Card Payment only) | Free mobile phone charging | I84: This location is Independent Access | Wheelchair ramp boarding assistance | Hearing loop | PA system for announcements | Platform edge tactiles | Stairs | Lift | Escalator | J84: 02 9851 7212 | K84: 6.30am-10am | L84: 3pm-7pm | M84: =TRUE() -> TRUE | N84: -33.768229 | O84: 150.90751
A85: Blackwattle Bay Wharf | B85: 203783 | C85: 10102058 | D85: Leichhardt St, Glebe NSW 2037 | E85: 2037 | F85: parsed from address | G85: Ferry | H85: Wheelchair accessible car space | Kiss and ride stopping area | Bike racks | No Opal card top up or single trip ticket sales | I85: This location is Assisted Access | Wheelchair ramp boarding assistance | Stairs | M85: =FALSE() -> FALSE | N85: -33.871362 | O85: 151.1852
A86: Blaxland Station | B86: 277410 | C86: 10101256 | D86: Station St, Blaxland NSW 2774 | E86: 2774 | F86: parsed from address | G86: Train, Bus, Taxi | H86: Commuter car park | Wheelchair accessible car space | Kiss and ride stopping area | Taxi rank | Bike racks | Bike lockers | Toilets | Wheelchair accessible toilet | Baby change table | Emergency help point | Information point | Payphone | Next service display | Opal card top up or single trip ticket machine (Card Payment only) | I86: This location is Assisted Access | Wheelchair ramp boarding assistance | Hearing loop | PA system for announcements | Platform edge tactiles | Stairs | Lift | J86: 02 4780 3253 | K86: 6am-10am | L86: 3pm-7pm | M86: =TRUE() -> TRUE | N86: -33.743577 | O86: 150.6096
A87: Blayney Station | B87: 27991 | C87: 10101813 | D87: Railway Lane, Blayney NSW 2799 | E87: 2799 | F87: parsed from address | G87: Train | H87: Commuter car park | Wheelchair accessible car space | Kiss and ride stopping area | Toilets | Wheelchair accessible toilet | Baby change table | Emergency help point | I87: This location is Independent Access | Wheelchair ramp boarding assistance | Hearing loop | Hearing loop (ticket counter) | PA system for announcements | Platform edge tactiles | Stairs | M87: =FALSE() -> FALSE | N87: -33.52704 | O87: 149.25452
A88: Blighty Coach Stop | B88: 271313 | C88: 10102832 | D88: Blighty Pub, Riverina Hwy, Blighty NSW 2713 | E88: 2713 | F88: parsed from address | G88: Coach | I88: This location is Not Accessible | | M88: =FALSE() -> FALSE | N88: -35.591983 | O88: 145.28722
A89: Bogan Gate Coach Stop | B89: 287646 | C89: 10102637 | D89: General Store, Station St, Bogan Gate NSW 2876 | E89: 2876 | F89: parsed from address | G89: Coach | I89: This location is Not Accessible | | M89: =FALSE() -> FALSE | N89: -33.107693 | O89: 147.80393
A90: Bogangar Coach Stop | B90: 248838 | C90: 10102732 | D90: Tweed Coast Rd opp Pandanus Pde, Bogangar NSW 2488 | E90: 2488 | F90: parsed from address | G90: Coach | I90: This location is Not Accessible | | M90: =FALSE() -> FALSE | N90: -28.332352 | O90: 153.5697
A91: Boggabri Station | B91: 23821 | C91: 10101817 | D91: Oakham St, Boggabri NSW 2382 | E91: 2382 | F91: parsed from address | G91: Train | H91: Commuter car park | Toilets | Information point | I91: This location is Independent Access | Wheelchair ramp boarding assistance | PA system for announcements | M91: =FALSE() -> FALSE | N91: -30.703834 | O91: 150.03983
A92: Bolivia Coach Stop | B92: 237212 | C92: 10102719 | D92: New England Hwy opp Mt Spirabo Rd, Bolivia NSW 2372 | E92: 2372 | F92: parsed from address | G92: Coach | I92: This location is Not Accessible | | M92: =FALSE() -> FALSE | N92: -29.289661 | O92: 151.96097
A93: Bomaderry Station | B93: 254110 | C93: 10101389 | D93: Meroo St, Bomaderry NSW 2541 | E93: 2541 | F93: parsed from address | G93: Train, Bus, Taxi | H93: Commuter car park | Wheelchair accessible car space | Taxi rank | Bike lockers | Toilets | Wheelchair accessible toilet | Baby change table | Emergency help point | Payphone | Opal card top up or single trip ticket machine (Cash or Card Payment) | I93: This location is Independent Access | Wheelchair ramp boarding assistance | Hearing loop | PA system for announcements | Platform edge tactiles | J93: 02 4423 0141 | K93: 6am-10am | L93: 3pm-7pm | M93: =TRUE() -> TRUE | N93: -34.853777 | O93: 150.60981
A94: Bombala Coach Stop | B94: 263226 | C94: 10102793 | D94: Forbes St at Maybe St, Bombala NSW 2632 | E94: 2632 | F94: parsed from address | G94: Coach | I94: This location is Not Accessible | | M94: =FALSE() -> FALSE | N94: -36.911161 | O94: 149.24032
A95: Bombo Station | B95: 253320 | C95: 10101385 | D95: Princes Hwy, Bombo NSW 2533 | E95: 2533 | F95: parsed from address | G95: Train, Taxi | H95: Commuter car park | Wheelchair accessible car space | Emergency help point | Information point | Payphone | No Opal card top up or single trip ticket sales | I95: This location is Independent Access | Wheelchair ramp boarding assistance | PA system for announcements | Platform edge tactiles | Stairs | J95: 02 4223 5613 | K95: 6am-10am | L95: 3pm-7pm | M95: =TRUE() -> TRUE | N95: -34.658029 | O95: 150.85398
A96: Bondi Junction Station | B96: 202210 | C96: 10101109 | D96: Grafton St, Bondi Junction NSW 2022 | E96: 2022 | F96: parsed from address | G96: Train, Bus, Taxi | H96: Taxi rank | Bike racks | Bike lockers | Toilets | Wheelchair accessible toilet | Baby change table | Emergency help point | Payphone | Next service display | Opal card top up or single trip ticket machine (Cash or Card Payment) | Opal card top up machine (Card Payment only) | Free mobile phone charging | I96: This location is Independent Access | Wheelchair ramp boarding assistance | Hearing loop | PA system for announcements | Platform edge tactiles | Stairs | Lift | Escalator | J96: 02 9379 4843 | K96: 6.30am-10am | L96: 3pm-7pm | M96: =TRUE() -> TRUE | N96: -33.891202 | O96: 151.24838
A97: Booragul Station | B97: 228410 | C97: 10101152 | D97: Station St, Booragul NSW 2284 | E97: 2284 | F97: parsed from address | G97: Train | H97: Emergency help point | Information point | No Opal card top up or single trip ticket sales | I97: This location is Not Accessible | Wheelchair ramp boarding assistance | Hearing loop | PA system for announcements | Platform edge tactiles | Stairs | J97: 02 4962 9437 | K97: 6am-10am | L97: 3pm-7pm | M97: =TRUE() -> TRUE | N97: -32.971423 | O97: 151.60469
A98: Booral Coach Stop | B98: 2425102 | C98: 10102779 | D98: The Bucketts Way at Booral Rd, Booral NSW 2425 | E98: 2425 | F98: parsed from address | G98: Coach | I98: This location is Not Accessible | | M98: =FALSE() -> FALSE | N98: -32.466585 | O98: 151.95947
A99: Boorowa Coach Stop | B99: 2586229 | C99: 10102869 | D99: Boorowa Court House, Marsden Street, Boorowa NSW 2586 | E99: 2586 | F99: parsed from address | G99: Coach | I99: This location is Not Accessible | | M99: =FALSE() -> FALSE | N99: -34.439297 | O99: 148.71621
A100: Boppy Mountain Coach Stop | B100: 283517 | C100: 10102605 | D100: Barrier Hwy after Booroomugga Rd, Canbelego NSW 2835 | E100: 2835 | F100: parsed from address | G100: Coach | I100: This location is Not Accessible | | M100: =FALSE() -> FALSE | N100: -31.531 | O100: 146.2831
...

Sheet Sports_Facilities
A1: FacilityName | B1: Suburb | C1: Postcode | D1: FacilityType | E1: Status | F1: Owner | G1: Sports & activities
A2: Alan Davidson Oval | B2: Alexandria | C2: 2015 | D2: Sports field | E2: Current | F2: City of Sydney | G2: AFL, Cricket
A3: Alexandria Park and Oval | B3: Alexandria | C3: 2015 | D3: Sports field, Tennis courts | E3: Current | F3: City of Sydney | G3: Basketball, Cricket, Netball, Rugby, Soccer, TennisCourts
A4: Andrew (Boy) Charlton Pool | B4: Sydney | C4: 2000 | D4: Pool | E4: Currently closed for renovation | F4: City of Sydney | G4: Pool
A5: Beaconsfield Park | B5: Beaconsfield | C5: 2015 | D5: Tennis courts | E5: Current | F5: City of Sydney | G5: Basketball, TennisCourts
A6: Bourke Street Park | B6: Woolloomooloo | C6: 2011 | D6: Park | E6: Current | F6: City of Sydney | G6: OutdoorGym
A7: Centennial Parklands | B7: Centennial Park | C7: 2021 | D7: Park | E7: Not managed by City of Sydney | F7: Centennial Park and Moore Park Trust | G7: AFL, Cricket, Hockey, OutdoorGym, Rugby, Soccer
A8: Centennial Parklands Sports Centre | B8: Moore Park | C8: 2021 | D8: Park | E8: Not managed by City of Sydney | F8: Centennial Park and Moore Park Trust | G8: AFL, Athletics, Basketball, Netball, Pickleball, Rugby, Soccer, TennisCourts
A9: Cliff Noble Community Centre | B9: Alexandria | C9: 2015 | D9: Community centre | E9: Current | F9: City of Sydney | G9: CityPrograms, TableTennis
A10: Cook + Phillip Park | B10: Sydney | C10: 2000 | D10: Park | E10: Current | F10: City of Sydney | G10: Basketball
A11: Cook + Phillip Park Pool | B11: Sydney | C11: 2000 | D11: Pool | E11: Current | F11: City of Sydney | G11: Badminton, Basketball, Futsal, IndoorGym, Netball, Pickleball, Pool, Volleyball
A12: Eddie Ward Park | B12: Surry Hills | C12: 2010 | D12: Park | E12: Current | F12: City of Sydney | G12: SkatePark, TableTennis
A13: Erskineville Oval | B13: Erskineville | C13: 2043 | D13: Sports field | E13: Current | F13: City of Sydney | G13: Athletics, Cricket, Rugby
... A71: Wulaba Park | B71: Waterloo | C71: 2017 | D71: Park | E71: Current | F71: City of Sydney | G71: TableTennis

Sheet Taxi_Ranks
A1: Rank_name | B1: Postcode | C1: Postcode_source | D1: Postcode_confidence | E1: Nearest_ref_m | F1: Latitude | G1: Longitude
A2: Allambie rank, Allambie Rd | B2: 2100 | C2: inferred: nearest EV/transport point | D2: high (<300m) | E2: 112 | F2: -33.765369 | G2: 151.24999
A3: Arncliffe, Firth St | B3: 2205 | C3: inferred: nearest EV/transport point | D3: high (<300m) | E3: 43 | F3: -33.936614 | G3: 151.14687
A4: Artarmon rank, Elizabeth St | B4: 2064 | C4: inferred: nearest EV/transport point | D4: high (<300m) | E4: 72 | F4: -33.808261 | G4: 151.1854
A5: Ashfield Rank, Hercules St | B5: 2131 | C5: inferred: nearest EV/transport point | D5: high (<300m) | E5: 66 | F5: -33.888146 | G5: 151.12551
A6: Auburn South Rank, South Parade | B6: 2144 | C6: inferred: nearest EV/transport point | D6: high (<300m) | E6: 44 | F6: -33.849239 | G6: 151.0324
A7: Avalon rank, Old Barrenjoey rd Avalon | B7: 2106 | C7: inferred: nearest EV/transport point | D7: low (>1km) | E7: 2711 | F7: -33.635878 | G7: 151.32961
A8: Balgowlah rank, Condamine St | B8: 2093 | C8: inferred: nearest EV/transport point | D8: high (<300m) | E8: 168 | F8: -33.794565 | G8: 151.26477
A9: Balgowlah Stocklands, Condamine St | B9: 2093 | C9: inferred: nearest EV/transport point | D9: high (<300m) | E9: 87 | F9: -33.793587 | G9: 151.26501
A10: Balmain Rank, Darling St | B10: 2041 | C10: inferred: nearest EV/transport point | D10: high (<300m) | E10: 70 | F10: -33.857399 | G10: 151.18071
A11: Bankstown Rank, North Terrace | B11: 2200 | C11: inferred: nearest EV/transport point | D11: high (<300m) | E11: 58 | F11: -33.917361 | G11: 151.03452
A12: Baulkham Hills Rank, Central Pl | B12: 2153 | C12: inferred: nearest EV/transport point | D12: high (<300m) | E12: 110 | F12: -33.7599 | G12: 150.99197
A13: Beecroft Rank, Hannah St | B13: 2119 | C13: inferred: nearest EV/transport point | D13: high (<300m) | E13: 93 | F13: -33.749355 | G13: 151.0656
... A199: Woolloomooloo rank, Cowper Wharf Rd | B199: 2011 | C199: inferred: nearest EV/transport point | D199: medium (300m-1km) | E199: 579 | F199: -33.869144 | G199: 151.22004

Sheet All_Points
A1: Dataset | B1: Name | C1: Address | D1: Postcode | E1: Postcode_source | F1: Latitude | G1: Longitude | H1: Detail
A2: EV charger | B2: NRMA charger | C2: 129 Pacific Hwy Ourimbah NSW 2258 | D2: 2258 | E2: parsed from address | F2: -33.353198 | G2: 151.36903 | H2: NRMA | Upcoming | 4 plug(s)
A3: EV charger | B3: NRMA charger | C3: 1-5 Hill Rd Sydney Olympic Park NSW 2127 | D3: 2127 | E3: parsed from address | F3: -33.846599 | G3: 151.05673 | H3: NRMA | Upcoming | 8 plug(s)
A4: EV charger | B4: NRMA charger | C4: 16 Cooper St Macksville NSW 2447 | D4: 2447 | E4: parsed from address | F4: -30.708461 | G4: 152.92007 | H4: NRMA | Upcoming | 4 plug(s)
A5: EV charger | B5: NRMA charger | C5: 2 Macquarie St Parramatta NSW 2150 | D5: 2150 | E5: parsed from address | F5: -33.81384 | G5: 150.99951 | H5: NRMA | Upcoming | 4 plug(s)
A6: EV charger | B6: NRMA charger | C6: 203 Holt Rd Taren Point NSW 2229 | D6: 2229 | E6: parsed from address | F6: -34.020269 | G6: 151.1171 | H6: NRMA | Upcoming | 4 plug(s)
A7: EV charger | B7: NRMA charger | C7: 25 Anglo Rd Campsie NSW 2194 | D7: 2194 | E7: parsed from address | F7: -33.911201 | G7: 151.10146 | H7: NRMA | Upcoming | 4 plug(s)
A8: EV charger | B8: NRMA charger | C8: 29 Church St, Maitland NSW 2320 | D8: 2320 | E8: parsed from address | F8: -32.732981 | G8: 151.55356 | H8: NRMA | Upcoming | 4 plug(s)
A9: EV charger | B9: NRMA charger | C9: 33 Village Cct Gregory Hills NSW 2557 | D9: 2557 | E9: parsed from address | F9: -34.026258 | G9: 150.77773 | H9: NRMA | Upcoming | 4 plug(s)
A10: EV charger | B10: NRMA charger | C10: 37-39 Bong Bong Street,, Dapto NSW 2023 | D10: 2023 | E10: parsed from address | F10: -34.494036 | G10: 150.79154 | H10: NRMA | Upcoming | 4 plug(s)
A11: EV charger | B11: NRMA charger | C11: 3A Cowell St Gladesville NSW 2111 | D11: 2111 | E11: parsed from address | F11: -33.832583 | G11: 151.12802 | H11: NRMA | Upcoming | 4 plug(s)
A12: EV charger | B12: NRMA charger | C12: 50 Pitt St Singleton NSW 2330 | D12: 2330 | E12: parsed from address | F12: -32.565117 | G12: 151.17446 | H12: NRMA | Upcoming | 4 plug(s)
A13: EV charger | B13: NRMA charger | C13: 57 Manchester Rd Gymea NSW 2227 | D13: 2227 | E13: parsed from address | F13: -34.032498 | G13: 151.08811 | H13: NRMA | Upcoming | 4 plug(s)
... A2756: Transport stop | B2756: Zig Zag Station | C2756: Inch St, Clarence NSW 2790 | D2756: 2790 | E2756: parsed from address | F2756: -33.47181 | G2756: 150.20209 | H2756: Train
A2757: Sports facility | B2757: Alan Davidson Oval | C2757: Alexandria | D2757: 2015 | E2757: original | H2757: Sports field
A2758: Sports facility | B2758: Alexandria Park and Oval | C2758: Alexandria | D2758: 2015 | E2758: original | H2758: Sports field, Tennis courts
A2759: Sports facility | B2759: Andrew (Boy) Charlton Pool | C2759: Sydney | D2759: 2000 | E2759: original | H2759: Pool
A2760: Sports facility | B2760: Beaconsfield Park | C2760: Beaconsfield | D2760: 2015 | E2760: original | H2760: Tennis courts
A2761: Sports facility | B2761: Bourke Street Park | C2761: Woolloomooloo | D2761: 2011 | E2761: original | H2761: Park
A2762: Sports facility | B2762: Centennial Parklands | C2762: Centennial Park | D2762: 2021 | E2762: original | H2762: Park
A2763: Sports facility | B2763: Centennial Parklands Sports Centre | C2763: Moore Park | D2763: 2021 | E2763: original | H2763: Park
A2764: Sports facility | B2764: Cliff Noble Community Centre | C2764: Alexandria | D2764: 2015 | E2764: original | H2764: Community centre
A2765: Sports facility | B2765: Cook + Phillip Park | C2765: Sydney | D2765: 2000 | E2765: original | H2765: Park
A2766: Sports facility | B2766: Cook + Phillip Park Pool | C2766: Sydney | D2766: 2000 | E2766: original | H2766: Pool
A2767: Sports facility | B2767: Eddie Ward Park | C2767: Surry Hills | D2767: 2010 | E2767: original | H2767: Park
A2768: Sports facility | B2768: Erskineville Oval | C2768: Erskineville | D2768: 2043 | E2768: original | H2768: Sports field
... A2826: Sports facility | B2826: Wulaba Park | C2826: Waterloo | D2826: 2017 | E2826: original | H2826: Park
A2827: Taxi rank | B2827: Allambie rank, Allambie Rd | D2827: 2100 | E2827: inferred: nearest EV/transport point (high (<300m)) | F2827: -33.765369 | G2827: 151.24999
A2828: Taxi rank | B2828: Arncliffe, Firth St | D2828: 2205 | E2828: inferred: nearest EV/transport point (high (<300m)) | F2828: -33.936614 | G2828: 151.14687
A2829: Taxi rank | B2829: Artarmon rank, Elizabeth St | D2829: 2064 | E2829: inferred: nearest EV/transport point (high (<300m)) | F2829: -33.808261 | G2829: 151.1854
A2830: Taxi rank | B2830: Ashfield Rank, Hercules St | D2830: 2131 | E2830: inferred: nearest EV/transport point (high (<300m)) | F2830: -33.888146 | G2830: 151.12551
A2831: Taxi rank | B2831: Auburn South Rank, South Parade | D2831: 2144 | E2831: inferred: nearest EV/transport point (high (<300m)) | F2831: -33.849239 | G2831: 151.0324
A2832: Taxi rank | B2832: Avalon rank, Old Barrenjoey rd Avalon | D2832: 2106 | E2832: inferred: nearest EV/transport point (low (>1km)) | F2832: -33.635878 | G2832: 151.32961
A2833: Taxi rank | B2833: Balgowlah rank, Condamine St | D2833: 2093 | E2833: inferred: nearest EV/transport point (high (<300m)) | F2833: -33.794565 | G2833: 151.26477
A2834: Taxi rank | B2834: Balgowlah Stocklands, Condamine St | D2834: 2093 | E2834: inferred: nearest EV/transport point (high (<300m)) | F2834: -33.793587 | G2834: 151.26501
A2835: Taxi rank | B2835: Balmain Rank, Darling St | D2835: 2041 | E2835: inferred: nearest EV/transport point (high (<300m)) | F2835: -33.857399 | G2835: 151.18071
A2836: Taxi rank | B2836: Bankstown Rank, North Terrace | D2836: 2200 | E2836: inferred: nearest EV/transport point (high (<300m)) | F2836: -33.917361 | G2836: 151.03452
A2837: Taxi rank | B2837: Baulkham Hills Rank, Central Pl | D2837: 2153 | E2837: inferred: nearest EV/transport point (high (<300m)) | F2837: -33.7599 | G2837: 150.99197
A2838: Taxi rank | B2838: Beecroft Rank, Hannah St | D2838: 2119 | E2838: inferred: nearest EV/transport point (high (<300m)) | F2838: -33.749355 | G2838: 151.0656
... A3024: Taxi rank | B3024: Woolloomooloo rank, Cowper Wharf Rd | D3024: 2011 | E3024: inferred: nearest EV/transport point (medium (300m-1km)) | F3024: -33.869144 | G3024: 151.22004
